hardware/mem_counter_test/mem_counters.sv
// img_mem_write    : done
// img_mem_read     : 
// conv1_k_mem_read : done
// conv1_mem_write  : done
// conv1_mem_read   : done?
// P1_mem_write     : done
// P1_mem_read      : 
// conv2_k_mem_read : 
// conv2_mem_write  : 
// conv2_mem_read   : 
// P2_mem_write     : 
// P2_mem_read      : 
// fc_mem_read      : done

// counter/addresser for input image memory write (done) //NOT NEEDED
module img_mem_write (input logic clk, reset, enable, next, 
                      output logic [9:0] addr0,  
                      output logic done, ack);

    always_ff @(posedge clk or posedge reset) begin
        if (reset == 1'b1) begin
            addr0 <= 10'b0000000000;
        end
        else if (enable == 1'b1 && done == 1'b0) begin
            addr0 <= addr0 + 1;
            ack <= 1'b1;
        end
        else if(next == 1'b1 && ack == 1'b1) begin
            ack <= 1'b0;
        end
    end

    always_comb begin
        if(addr0 == 10'b1100001111) begin
            done = 1'b1;
        end
    end

endmodule

//img_mem_read is responsible for one conv1 output image and uses four output addresses in parallel. Each processes a quarter of the image, the offset between addresses is 28 * 24 / 4 = 168
// counter/addresser for input image memory read
module img_mem_read (input logic clk, reset, enable,
                     output logic [9:0] addr0, addr1, addr2, addr3, 
                     output logic done);

    //kernel row and column count
    logic [2:0] rowcount, columncount;
    //counter for position within image row
    logic [4:0] i_count;

    always_ff @(posedge clk or posedge reset) begin
        if (reset == 1'b1) begin
            addr0 <= 10'b0000000000;
            addr1 <= 10'b0010101000;
            addr2 <= 10'b0101010000;
            addr3 <= 10'b0111111000;
            i_count <= 5'b00000;
        end
        else if (enable == 1'b1 && done == 1'b0) begin
            if (i_count == 5'b10111 && rowcount == 3'b100 && columncount == 3'b100) begin
                //done with applying the kernel over an entire image row, go to the next row
                //Move addresses 4 rows up, 27 pixels back and 1 row down, i.e. -111
                i_count <= 5'b0000;
                columncount <= 3'b000;
                rowcount <= 3'b000;
                addr0 <= addr0 - 10'b0001101111;
                addr1 <= addr1 - 10'b0001101111;
                addr2 <= addr2 - 10'b0001101111;
                addr3 <= addr3 - 10'b0001101111;
            end
            else if (rowcount == 3'b100 && columncount == 3'b100) begin
                //done with a position for the kernel, move forward to the next position. Move 4 rows up, 4 pixels back and 1 pixel forward, i.e. -115
                columncount <= 3'b000;
                rowcount <= 3'b000;
                addr0 <= addr0 - 10'b0001110011;
                addr1 <= addr1 - 10'b0001110011;
                addr2 <= addr2 - 10'b0001110011;
                addr3 <= addr3 - 10'b0001110011;
                i_count <= i_count + 5'b00001;
            end
            else if (columncount == 3'b100) begin
                //kernel row has been processed, move addresses one row down and 4 pixels back, i.e. + 24
                columncount <= 3'b000;
                rowcount <= rowcount + 3'b001;
                addr0 <= addr0 + 10'b0000011000;
                addr1 <= addr1 + 10'b0000011000;
                addr2 <= addr2 + 10'b0000011000;
                addr3 <= addr3 + 10'b0000011000;
            end
            else begin
                addr0 <= addr0 + 10'b0000000001;
                addr1 <= addr1 + 10'b0000000001;
                addr2 <= addr2 + 10'b0000000001;
                addr3 <= addr3 + 10'b0000000001;
                columncount <= columncount + 3'b001;
            end
        end
    end

    always_comb begin
        if(addr3 == 10'b1100001111) begin
            done = 1'b1;
        end
    end

endmodule

// counter/addresser for Convolution 1 layer weight memory read (done)
module conv1_k_mem_read (input logic clk, reset, enable, 
                        output logic [5:0] addr0, addr1, 
                        output logic done);

    always_ff @(posedge clk or posedge reset) begin
        if (reset == 1'b1) begin
            addr0 <= 6'b000000;
            addr1 <= 6'b011001;
        end
        else if (enable == 1'b1 && done == 1'b0) begin
            addr0 <= addr0 + 6'b000001;
            addr1 <= addr1 + 6'b000001;
        end
    end

    always_comb begin
        if(addr1 == 6'b110001) begin
            done = 1'b1;
        end
    end

endmodule

// counter/addresser for Convolution 1 layer output memory write (done)
module conv1_mem_write (input logic clk, reset, enable,
                        output logic [9:0] addr0, addr1, 
                        output logic done);

    always_ff @(posedge clk or posedge reset) begin
        if (reset == 1'b1) begin
            addr0 <= 10'b0000000000;
            addr1 <= 10'b0010010000;
        end
        else if (enable == 1'b1 && done == 1'b0) begin
            addr0 <= addr0 + 10'b0000000001;
            addr1 <= addr1 + 10'b0000000001;
        end
    end

    always_comb begin
        if(addr1 == 10'b1000111111) begin
            done = 1'b1;
        end
    end

endmodule

// counter/addresser for Convolution 1 layer output memory read (done?)
module conv1_mem_read (input logic clk, reset, enable,
                        output logic [9:0] addr0, addr1, addr2, addr3, 
                        output logic done);

    logic [3:0] count;
    always_ff @(posedge clk or posedge reset) begin
        if (reset == 1'b1) begin
            addr0 <= 10'b0000000000;
            addr1 <= 10'b0000000001;
            addr2 <= 10'b0000011000;
            addr3 <= 10'b0000011001;
            count <= 4'b0000;
        end
        
        else if (enable == 1'b1 && done == 1'b0) begin
            if(count == 4'b1011) begin
                count <= 4'b0000;
                addr0 <= addr0 + 10'b0000011010;
                addr1 <= addr1 + 10'b0000011010;
                addr2 <= addr2 + 10'b0000011010;
                addr3 <= addr3 + 10'b0000011010;
            end
            else begin    
                addr0 <= addr0 + 10'b0000000010;
                addr1 <= addr1 + 10'b0000000010;
                addr2 <= addr2 + 10'b0000000010;
                addr3 <= addr3 + 10'b0000000010;
                count <= count + 4'b0001;
            end
        end
    end
    
    always_comb begin
        //stop when addr3 == 24^2 - 1, i.e. we have processed the entire image
        if(addr3 == 10'b1000111111) begin
            done = 1'b1;
        end
    end

endmodule

// counter/addresser for pooling 1 layer output memory write (done)
module P1_mem_write (input logic clk, reset, enable,
                        output logic [7:0] addr0, addr1,
                        output logic done);

    always_ff @(posedge clk or posedge reset) begin
        if (reset == 1'b1) begin
            addr0 <= 8'b00000000;
            addr1 <= 8'b01001000;
        end
        else if (enable == 1'b1 && done == 1'b0) begin
            addr0 <= addr0 + 8'b00000001;
            addr1 <= addr1 + 8'b00000001;
        end
    end
    
    always_comb begin
        //stop when addr1 == 12^2 - 1, i.e. we have processed the entire image
        if(addr1 == 8'b10001111) begin
            done = 1'b1;
        end
    end

endmodule

//P1_mem_read is responsible for one conv2 output image and uses two output addresses in parallel. Each processes half of the image, the offset between addresses is 12 * 8 / 2 = 48
// counter/addresser for pooling 1 layer output memory read
module P1_mem_read (input logic clk, reset, enable,
                        output logic [7:0] addr0, addr1,
                        output logic done);
    //kernel row and column count
    logic [2:0] rowcount, columncount;
    //counter for position within image row
    logic [2:0] i_count;

    always_ff @(posedge clk or posedge reset) begin
        if (reset == 1'b1) begin
            addr0 <= 8'b00000000;
            addr1 <= 8'b00110000;
            i_count <= 3'b000;
        end
        else if (enable == 1'b1 && done == 1'b0) begin
            if (i_count == 3'b111 && rowcount == 3'b100 && columncount == 3'b100) begin
                //done with applying the kernel over an entire image row, go to the next row
                //Move addresses 4 rows up, 11 pixels back and 1 row down, i.e. -47
                i_count <= 3'b000;
                columncount <= 3'b000;
                rowcount <= 3'b000;
                addr0 <= addr0 - 8'b00101111;
                addr1 <= addr1 - 8'b00101111;
            end
            else if (rowcount == 3'b100 && columncount == 3'b100) begin
                //done with a position for the kernel, move forward to the next position. Move 4 rows up, 4 pixels back and 1 pixel forward, i.e. -51
                columncount <= 3'b000;
                rowcount <= 3'b000;
                addr0 <= addr0 - 8'b00110011;
                addr1 <= addr1 - 8'b00110011;
                i_count <= i_count + 3'b001;
            end
            else if (columncount == 3'b100) begin
                //kernel row has been processed, move addresses one row down and 4 pixels back, i.e. + 8
                columncount <= 3'b000;
                rowcount <= rowcount + 3'b001;
                addr0 <= addr0 + 8'b00001000;
                addr1 <= addr1 + 8'b00001000;
            end
            else begin
                addr0 <= addr0 + 8'b00000001;
                addr1 <= addr1 + 8'b00000001;
                columncount <= columncount + 3'b001;
            end
        end
    end
    
    always_comb begin
        if(addr1 == 8'b10001111) begin
            done = 1'b1;
        end
    end

endmodule

//Module used to provide access to 6 kernels with two counters at once
// counter/addresser for Convolution 2 layer weight memory read
module conv2_k_mem_read (input logic clk, reset, enable,
                        output logic [7:0] addr0, addr1,
                        output logic done);

    always_ff @(posedge clk or posedge reset) begin
        if (reset == 1'b1) begin
            addr0 <= 8'b00000000;
            addr1 <= 8'b01001011;
        end
        else if (enable == 1'b1 && done == 1'b0) begin
            addr0 <= addr0 + 8'b00000001;
            addr1 <= addr1 + 8'b00000001;
        end
    end
    
    always_comb begin
        //Count until addr1 reaches end of 6th kernel, i.e. 6 * 25 - 1 = 149
        if(addr1 == 8'b10010101) begin
            done = 1'b1;
        end
    end

endmodule

//Go through an 8x8 output image 3 times
// counter/addresser for Convolution 2 layer output memory write
module conv2_mem_write (input logic clk, reset, enable,
                        output logic [5:0] addr0,
                        output logic done);
    logic [1:0] count;

    always_ff @(posedge clk or posedge reset) begin
        if (reset == 1'b1) begin
            addr0 <= 6'b000000;
            count <= 2'b00;
        end
        else if (enable == 1'b1 && done == 1'b0) begin
            if(addr0 == 6'b111111) begin
                count <= count + 2'b01;
                addr0 <= 6'b000000;
            end
            else begin
                addr0 <= addr0 + 6'b000001;
            end
        end
    end
    
    always_comb begin
        if(count == 2'b10 && addr0 == 6'b111111) begin
            done = 1'b1;
        end
    end

endmodule

// counter/addresser for Convolution 2 layer output memory read (done)
module conv2_mem_read (input logic clk, reset, enable,
                        output logic [5:0] addr0, addr1, addr2, addr3,
                        output logic done);

    logic [1:0] count;
    always_ff @(posedge clk or posedge reset) begin
        if (reset == 1'b1) begin
            addr0 <= 6'b000000;
            addr1 <= 6'b000001;
            addr2 <= 6'b001000;
            addr3 <= 6'b001001;
            count <= 2'b00;
        end

        else if (enable == 1'b1 && done == 1'b0) begin
            if(count == 2'b11) begin
                count <= 2'b00;
                addr0 <= addr0 + 6'b001010;
                addr1 <= addr1 + 6'b001010;
                addr2 <= addr2 + 6'b001010;
                addr3 <= addr3 + 6'b001010;
            end
            else begin
                addr0 <= addr0 + 6'b000010;
                addr1 <= addr1 + 6'b000010;
                addr2 <= addr2 + 6'b000010;
                addr3 <= addr3 + 6'b000010;
                count <= count + 2'b01;
            end
        end
    end
    
    always_comb begin
        //stop when addr3 == 8^2 - 1, i.e. we have processed the entire image
        if(addr3 == 6'b111111) begin
            done = 1'b1;
        end
    end

endmodule

// counter/addresser for pooling 2 layer output memory write (done)
module P2_mem_write (input logic clk, reset, enable,
                        output logic [3:0] addr0,
                        output logic done);

    always_ff @(posedge clk or posedge reset) begin
        if (reset == 1'b1) begin
            addr0 <= 4'b0000;
        end
        else if (enable == 1'b1 && done == 1'b0) begin
            addr0 <= addr0 + 4'b0001;
        end
    end
    
    always_comb begin
        //stop when addr1 == 4^2 - 1, i.e. we have processed the entire image
        if(addr0 == 4'b1111) begin
            done = 1'b1;
        end
    end

endmodule

//cycle through 4x4 input images 12 times
// counter/addresser for pooling 2 layer output memory read
module P2_mem_read (input logic clk, reset, enable,
                        output logic [3:0] addr0,
                        output logic done);
    logic [3:0] count;

    always_ff @(posedge clk or posedge reset) begin
        if (reset == 1'b1) begin
            count <= 4'b0000;
            addr0 <= 4'b0000;
        end
        else if (enable == 1'b1 && done == 1'b0) begin
            if(addr0 == 4'b1111) begin
                count <= count + 4'b0001;
                addr0 <= 4'b0000;
            end
            else begin
                addr0 <= addr0 + 4'b0001;
            end
        end
    end

    always_comb begin
        if(count == 4'b1011 && addr0 == 4'b1111) begin
            done = 1'b1;
        end
    end

endmodule

// counter/addresser for Fully connected layer weight memory read (done)
module fc_mem_read (input logic clk, reset, enable, 
                        output logic [8:0] addr0, addr1, 
                        output logic done);

    always_ff @(posedge clk or posedge reset) begin
        if (reset == 1'b1) begin
            addr0 <= 9'b000000000;
            addr1 <= 9'b011000000;
        end
        else if (enable == 1'b1 && done == 1'b0) begin
            addr0 <= addr0 + 9'b000000001;
            addr1 <= addr1 + 9'b000000001;
        end
    end

    always_comb begin
        if(addr1 == 9'b101111111)
            done = 1'b1;
    end

endmodule

hardware/mem_counter_test/conv2_mem_write.vcd
$version Generated by VerilatedVcd $end
$date Thu May  5 10:33:27 2022
 $end
$timescale   1ns $end

 $scope module TOP $end
  $var wire  6 ' addr0 [5:0] $end
  $var wire  1 $ clk $end
  $var wire  1 ( done $end
  $var wire  1 & enable $end
  $var wire  1 % reset $end
  $scope module conv2_mem_write $end
   $var wire  6 ' addr0 [5:0] $end
   $var wire  1 $ clk $end
   $var wire  2 # count [1:0] $end
   $var wire  1 ( done $end
   $var wire  1 & enable $end
   $var wire  1 % reset $end
  $upscope $end
 $upscope $end
$enddefinitions $end


#0
b00 #
0$
0%
0&
b000000 '
0(
#10
1$
#20
0$
1%
#30
1$
#40
0$
#50
1$
#60
0$
0%
#70
1$
#80
0$
1&
#90
1$
b000001 '
#90
#100
0$
#110
1$
b000010 '
#120
0$
#130
1$
b000011 '
#140
0$
#150
1$
b000100 '
#160
0$
#170
1$
b000101 '
#180
0$
#190
1$
b000110 '
#200
0$
#210
1$
b000111 '
#220
0$
#230
1$
b001000 '
#240
0$
#250
1$
b001001 '
#260
0$
#270
1$
b001010 '
#280
0$
#290
1$
b001011 '
#300
0$
#310
1$
b001100 '
#320
0$
#330
1$
b001101 '
#340
0$
#350
1$
b001110 '
#360
0$
#370
1$
b001111 '
#380
0$
#390
1$
b010000 '
#400
0$
#410
1$
b010001 '
#420
0$
#430
1$
b010010 '
#440
0$
#450
1$
b010011 '
#460
0$
#470
1$
b010100 '
#480
0$
#490
1$
b010101 '
#500
0$
#510
1$
b010110 '
#520
0$
#530
1$
b010111 '
#540
0$
#550
1$
b011000 '
#560
0$
#570
1$
b011001 '
#580
0$
#590
1$
b011010 '
#600
0$
#610
1$
b011011 '
#620
0$
#630
1$
b011100 '
#640
0$
#650
1$
b011101 '
#660
0$
#670
1$
b011110 '
#680
0$
#690
1$
b011111 '
#700
0$
#710
1$
b100000 '
#720
0$
#730
1$
b100001 '
#740
0$
#750
1$
b100010 '
#760
0$
#770
1$
b100011 '
#780
0$
#790
1$
b100100 '
#800
0$
#810
1$
b100101 '
#820
0$
#830
1$
b100110 '
#840
0$
#850
1$
b100111 '
#860
0$
#870
1$
b101000 '
#880
0$
#890
1$
b101001 '
#900
0$
#910
1$
b101010 '
#920
0$
#930
1$
b101011 '
#940
0$
#950
1$
b101100 '
#960
0$
#970
1$
b101101 '
#980
0$
#990
1$
b101110 '
#1000
0$
#1010
1$
b101111 '
#1020
0$
#1030
1$
b110000 '
#1040
0$
#1050
1$
b110001 '
#1060
0$
#1070
1$
b110010 '
#1080
0$
#1090
1$
b110011 '
#1100
0$
#1110
1$
b110100 '
#1120
0$
#1130
1$
b110101 '
#1140
0$
#1150
1$
b110110 '
#1160
0$
#1170
1$
b110111 '
#1180
0$
#1190
1$
b111000 '
#1200
0$
#1210
1$
b111001 '
#1220
0$
#1230
1$
b111010 '
#1240
0$
#1250
1$
b111011 '
#1260
0$
#1270
1$
b111100 '
#1280
0$
#1290
1$
b111101 '
#1300
0$
#1310
1$
b111110 '
#1320
0$
#1330
1$
b111111 '
#1340
0$
#1350
b01 #
1$
b000000 '
#1360
0$
#1370
1$
b000001 '
#1380
0$
#1390
1$
b000010 '
#1400
0$
#1410
1$
b000011 '
#1420
0$
#1430
1$
b000100 '
#1440
0$
#1450
1$
b000101 '
#1460
0$
#1470
1$
b000110 '
#1480
0$
#1490
1$
b000111 '
#1500
0$
#1510
1$
b001000 '
#1520
0$
#1530
1$
b001001 '
#1540
0$
#1550
1$
b001010 '
#1560
0$
#1570
1$
b001011 '
#1580
0$
#1590
1$
b001100 '
#1600
0$
#1610
1$
b001101 '
#1620
0$
#1630
1$
b001110 '
#1640
0$
#1650
1$
b001111 '
#1660
0$
#1670
1$
b010000 '
#1680
0$
#1690
1$
b010001 '
#1700
0$
#1710
1$
b010010 '
#1720
0$
#1730
1$
b010011 '
#1740
0$
#1750
1$
b010100 '
#1760
0$
#1770
1$
b010101 '
#1780
0$
#1790
1$
b010110 '
#1800
0$
#1810
1$
b010111 '
#1820
0$
#1830
1$
b011000 '
#1840
0$
#1850
1$
b011001 '
#1860
0$
#1870
1$
b011010 '
#1880
0$
#1890
1$
b011011 '
#1900
0$
#1910
1$
b011100 '
#1920
0$
#1930
1$
b011101 '
#1940
0$
#1950
1$
b011110 '
#1960
0$
#1970
1$
b011111 '
#1980
0$
#1990
1$
b100000 '
#2000
0$
#2010
1$
b100001 '
#2020
0$
#2030
1$
b100010 '
#2040
0$
#2050
1$
b100011 '
#2060
0$
#2070
1$
b100100 '
#2080
0$
#2090
1$
b100101 '
#2100
0$
#2110
1$
b100110 '
#2120
0$
#2130
1$
b100111 '
#2140
0$
#2150
1$
b101000 '
#2160
0$
#2170
1$
b101001 '
#2180
0$
#2190
1$
b101010 '
#2200
0$
#2210
1$
b101011 '
#2220
0$
#2230
1$
b101100 '
#2240
0$
#2250
1$
b101101 '
#2260
0$
#2270
1$
b101110 '
#2280
0$
#2290
1$
b101111 '
#2300
0$
#2310
1$
b110000 '
#2320
0$
#2330
1$
b110001 '
#2340
0$
#2350
1$
b110010 '
#2360
0$
#2370
1$
b110011 '
#2380
0$
#2390
1$
b110100 '
#2400
0$
#2410
1$
b110101 '
#2420
0$
#2430
1$
b110110 '
#2440
0$
#2450
1$
b110111 '
#2460
0$
#2470
1$
b111000 '
#2480
0$
#2490
1$
b111001 '
#2500
0$
#2510
1$
b111010 '
#2520
0$
#2530
1$
b111011 '
#2540
0$
#2550
1$
b111100 '
#2560
0$
#2570
1$
b111101 '
#2580
0$
#2590
1$
b111110 '
#2600
0$
#2610
1$
b111111 '
#2620
0$
#2630
b10 #
1$
b000000 '
#2640
0$
#2650
1$
b000001 '
#2660
0$
#2670
1$
b000010 '
#2680
0$
#2690
1$
b000011 '
#2700
0$
#2710
1$
b000100 '
#2720
0$
#2730
1$
b000101 '
#2740
0$
#2750
1$
b000110 '
#2760
0$
#2770
1$
b000111 '
#2780
0$
#2790
1$
b001000 '
#2800
0$
#2810
1$
b001001 '
#2820
0$
#2830
1$
b001010 '
#2840
0$
#2850
1$
b001011 '
#2860
0$
#2870
1$
b001100 '
#2880
0$
#2890
1$
b001101 '
#2900
0$
#2910
1$
b001110 '
#2920
0$
#2930
1$
b001111 '
#2940
0$
#2950
1$
b010000 '
#2960
0$
#2970
1$
b010001 '
#2980
0$
#2990
1$
b010010 '
#3000
0$
#3010
1$
b010011 '
#3020
0$
#3030
1$
b010100 '
#3040
0$
#3050
1$
b010101 '
#3060
0$
#3070
1$
b010110 '
#3080
0$
#3090
1$
b010111 '
#3100
0$
#3110
1$
b011000 '
#3120
0$
#3130
1$
b011001 '
#3140
0$
#3150
1$
b011010 '
#3160
0$
#3170
1$
b011011 '
#3180
0$
#3190
1$
b011100 '
#3200
0$
#3210
1$
b011101 '
#3220
0$
#3230
1$
b011110 '
#3240
0$
#3250
1$
b011111 '
#3260
0$
#3270
1$
b100000 '
#3280
0$
#3290
1$
b100001 '
#3300
0$
#3310
1$
b100010 '
#3320
0$
#3330
1$
b100011 '
#3340
0$
#3350
1$
b100100 '
#3360
0$
#3370
1$
b100101 '
#3380
0$
#3390
1$
b100110 '
#3400
0$
#3410
1$
b100111 '
#3420
0$
#3430
1$
b101000 '
#3440
0$
#3450
1$
b101001 '
#3460
0$
#3470
1$
b101010 '
#3480
0$
#3490
1$
b101011 '
#3500
0$
#3510
1$
b101100 '
#3520
0$
#3530
1$
b101101 '
#3540
0$
#3550
1$
b101110 '
#3560
0$
#3570
1$
b101111 '
#3580
0$
#3590
1$
b110000 '
#3600
0$
#3610
1$
b110001 '
#3620
0$
#3630
1$
b110010 '
#3640
0$
#3650
1$
b110011 '
#3660
0$
#3670
1$
b110100 '
#3680
0$
#3690
1$
b110101 '
#3700
0$
#3710
1$
b110110 '
#3720
0$
#3730
1$
b110111 '
#3740
0$
#3750
1$
b111000 '
#3760
0$
#3770
1$
b111001 '
#3780
0$
#3790
1$
b111010 '
#3800
0$
#3810
1$
b111011 '
#3820
0$
#3830
1$
b111100 '
#3840
0$
#3850
1$
b111101 '
#3860
0$
#3870
1$
b111110 '
#3880
0$
#3890
1$
b111111 '
1(
