hardware/mem_counter_test/mem_counters.sv
// img_mem_write    : done
// img_mem_read     : 
// conv1_k_mem_read : done
// conv1_mem_write  : done
// conv1_mem_read   : done?
// P1_mem_write     : done
// P1_mem_read      : 
// conv2_k_mem_read : 
// conv2_mem_write  : 
// conv2_mem_read   : 
// P2_mem_write     : 
// P2_mem_read      : 
// fc_mem_read      : done

// counter/addresser for input image memory write (done) //NOT NEEDED
module img_mem_write (input logic clk, reset, enable, next, 
                      output logic [9:0] addr0,  
                      output logic done, ack);

    always_ff @(posedge clk or posedge reset) begin
        if (reset == 1'b1) begin
            addr0 <= 10'b0000000000;
        end
        else if (enable == 1'b1 && done == 1'b0) begin
            addr0 <= addr0 + 1;
            ack <= 1'b1;
        end
        else if(next == 1'b1 && ack == 1'b1) begin
            ack <= 1'b0;
        end
    end

    always_comb begin
        if(addr0 == 10'b1100001111) begin
            done = 1'b1;
        end
    end

endmodule

//img_mem_read is responsible for one conv1 output image and uses four output addresses in parallel. Each processes a quarter of the image, the offset between addresses is 28 * 24 / 4 = 168
// counter/addresser for input image memory read
module img_mem_read (input logic clk, reset, enable,
                     output logic [9:0] addr0, addr1, addr2, addr3, 
                     output logic done);

    //kernel row and column count
    logic [2:0] rowcount, columncount;
    //counter for position within image row
    logic [4:0] i_count;

    always_ff @(posedge clk or posedge reset) begin
        if (reset == 1'b1) begin
            addr0 <= 10'b0000000000;
            addr1 <= 10'b0010101000;
            addr2 <= 10'b0101010000;
            addr3 <= 10'b0111111000;
            i_count <= 5'b00000;
        end
        else if (enable == 1'b1 && done == 1'b0) begin
            if (i_count == 5'b10111 && rowcount == 3'b100 && columncount == 3'b100) begin
                //done with applying the kernel over an entire image row, go to the next row
                //Move addresses 4 rows up, 27 pixels back and 1 row down, i.e. -111
                i_count <= 5'b0000;
                columncount <= 3'b000;
                rowcount <= 3'b000;
                addr0 <= addr0 - 10'b0001101111;
                addr1 <= addr1 - 10'b0001101111;
                addr2 <= addr2 - 10'b0001101111;
                addr3 <= addr3 - 10'b0001101111;
            end
            else if (rowcount == 3'b100 && columncount == 3'b100) begin
                //done with a position for the kernel, move forward to the next position. Move 4 rows up, 4 pixels back and 1 pixel forward, i.e. -115
                columncount <= 3'b000;
                rowcount <= 3'b000;
                addr0 <= addr0 - 10'b0001110011;
                addr1 <= addr1 - 10'b0001110011;
                addr2 <= addr2 - 10'b0001110011;
                addr3 <= addr3 - 10'b0001110011;
                i_count <= i_count + 5'b00001;
            end
            else if (columncount == 3'b100) begin
                //kernel row has been processed, move addresses one row down and 4 pixels back, i.e. + 24
                columncount <= 3'b000;
                rowcount <= rowcount + 3'b001;
                addr0 <= addr0 + 10'b0000011000;
                addr1 <= addr1 + 10'b0000011000;
                addr2 <= addr2 + 10'b0000011000;
                addr3 <= addr3 + 10'b0000011000;
            end
            else begin
                addr0 <= addr0 + 10'b0000000001;
                addr1 <= addr1 + 10'b0000000001;
                addr2 <= addr2 + 10'b0000000001;
                addr3 <= addr3 + 10'b0000000001;
                columncount <= columncount + 3'b001;
            end
        end
    end

    always_comb begin
        if(addr3 == 10'b1100001111) begin
            done = 1'b1;
        end
    end

endmodule

// counter/addresser for Convolution 1 layer weight memory read (done)
module conv1_k_mem_read (input logic clk, reset, enable, 
                        output logic [5:0] addr0, addr1, 
                        output logic done);

    always_ff @(posedge clk or posedge reset) begin
        if (reset == 1'b1) begin
            addr0 <= 6'b000000;
            addr1 <= 6'b011001;
        end
        else if (enable == 1'b1 && done == 1'b0) begin
            addr0 <= addr0 + 6'b000001;
            addr1 <= addr1 + 6'b000001;
        end
    end

    always_comb begin
        if(addr1 == 6'b110001) begin
            done = 1'b1;
        end
    end

endmodule

// counter/addresser for Convolution 1 layer output memory write (done)
module conv1_mem_write (input logic clk, reset, enable,
                        output logic [9:0] addr0, addr1, 
                        output logic done);

    always_ff @(posedge clk or posedge reset) begin
        if (reset == 1'b1) begin
            addr0 <= 10'b0000000000;
            addr1 <= 10'b0010010000;
        end
        else if (enable == 1'b1 && done == 1'b0) begin
            addr0 <= addr0 + 10'b0000000001;
            addr1 <= addr1 + 10'b0000000001;
        end
    end

    always_comb begin
        if(addr1 == 10'b1000111111) begin
            done = 1'b1;
        end
    end

endmodule

// counter/addresser for Convolution 1 layer output memory read (done?)
module conv1_mem_read (input logic clk, reset, enable,
                        output logic [9:0] addr0, addr1, addr2, addr3, 
                        output logic done);

    logic [3:0] count;
    always_ff @(posedge clk or posedge reset) begin
        if (reset == 1'b1) begin
            addr0 <= 10'b0000000000;
            addr1 <= 10'b0000000001;
            addr2 <= 10'b0000011000;
            addr3 <= 10'b0000011001;
            count <= 4'b0000;
        end
        
        else if (enable == 1'b1 && done == 1'b0) begin
            if(count == 4'b1011) begin
                count <= 4'b0000;
                addr0 <= addr0 + 10'b0000011010;
                addr1 <= addr1 + 10'b0000011010;
                addr2 <= addr2 + 10'b0000011010;
                addr3 <= addr3 + 10'b0000011010;
            end
            else begin    
                addr0 <= addr0 + 10'b0000000010;
                addr1 <= addr1 + 10'b0000000010;
                addr2 <= addr2 + 10'b0000000010;
                addr3 <= addr3 + 10'b0000000010;
                count <= count + 4'b0001;
            end
        end
    end
    
    always_comb begin
        //stop when addr3 == 24^2 - 1, i.e. we have processed the entire image
        if(addr3 == 10'b1000111111) begin
            done = 1'b1;
        end
    end

endmodule

// counter/addresser for pooling 1 layer output memory write (done)
module P1_mem_write (input logic clk, reset, enable,
                        output logic [7:0] addr0, addr1,
                        output logic done);

    always_ff @(posedge clk or posedge reset) begin
        if (reset == 1'b1) begin
            addr0 <= 8'b00000000;
            addr1 <= 8'b01001000;
        end
        else if (enable == 1'b1 && done == 1'b0) begin
            addr0 <= addr0 + 8'b00000001;
            addr1 <= addr1 + 8'b00000001;
        end
    end
    
    always_comb begin
        //stop when addr1 == 12^2 - 1, i.e. we have processed the entire image
        if(addr1 == 8'b10001111) begin
            done = 1'b1;
        end
    end

endmodule

//P1_mem_read is responsible for one conv2 output image and uses two output addresses in parallel. Each processes half of the image, the offset between addresses is 12 * 8 / 2 = 48
// counter/addresser for pooling 1 layer output memory read
module P1_mem_read (input logic clk, reset, enable,
                        output logic [7:0] addr0, addr1,
                        output logic done);
    //kernel row and column count
    logic [2:0] rowcount, columncount;
    //counter for position within image row
    logic [2:0] i_count;

    always_ff @(posedge clk or posedge reset) begin
        if (reset == 1'b1) begin
            addr0 <= 8'b00000000;
            addr1 <= 8'b00110000;
            i_count <= 3'b000;
        end
        else if (enable == 1'b1 && done == 1'b0) begin
            if (i_count == 3'b111 && rowcount == 3'b100 && columncount == 3'b100) begin
                //done with applying the kernel over an entire image row, go to the next row
                //Move addresses 4 rows up, 11 pixels back and 1 row down, i.e. -47
                i_count <= 3'b000;
                columncount <= 3'b000;
                rowcount <= 3'b000;
                addr0 <= addr0 - 8'b00101111;
                addr1 <= addr1 - 8'b00101111;
            end
            else if (rowcount == 3'b100 && columncount == 3'b100) begin
                //done with a position for the kernel, move forward to the next position. Move 4 rows up, 4 pixels back and 1 pixel forward, i.e. -51
                columncount <= 3'b000;
                rowcount <= 3'b000;
                addr0 <= addr0 - 8'b00110011;
                addr1 <= addr1 - 8'b00110011;
                i_count <= i_count + 3'b001;
            end
            else if (columncount == 3'b100) begin
                //kernel row has been processed, move addresses one row down and 4 pixels back, i.e. + 8
                columncount <= 3'b000;
                rowcount <= rowcount + 3'b001;
                addr0 <= addr0 + 8'b00001000;
                addr1 <= addr1 + 8'b00001000;
            end
            else begin
                addr0 <= addr0 + 8'b00000001;
                addr1 <= addr1 + 8'b00000001;
                columncount <= columncount + 3'b001;
            end
        end
    end
    
    always_comb begin
        if(addr1 == 8'b10001111) begin
            done = 1'b1;
        end
    end

endmodule

//Module used to provide access to 6 kernels with two counters at once
// counter/addresser for Convolution 2 layer weight memory read
module conv2_k_mem_read (input logic clk, reset, enable,
                        output logic [7:0] addr0, addr1,
                        output logic done);

    always_ff @(posedge clk or posedge reset) begin
        if (reset == 1'b1) begin
            addr0 <= 8'b00000000;
            addr1 <= 8'b01001011;
        end
        else if (enable == 1'b1 && done == 1'b0) begin
            addr0 <= addr0 + 8'b00000001;
            addr1 <= addr1 + 8'b00000001;
        end
    end
    
    always_comb begin
        //Count until addr1 reaches end of 6th kernel, i.e. 6 * 25 - 1 = 149
        if(addr1 == 8'b10010101) begin
            done = 1'b1;
        end
    end

endmodule

//Go through an 8x8 output image 3 times
// counter/addresser for Convolution 2 layer output memory write
module conv2_mem_write (input logic clk, reset, enable,
                        output logic [5:0] addr0,
                        output logic done);
    logic [1:0] count;

    always_ff @(posedge clk or posedge reset) begin
        if (reset == 1'b1) begin
            addr0 <= 6'b000000;
            count <= 2'b00;
        end
        else if (enable == 1'b1 && done == 1'b0) begin
            if(addr0 == 6'b111111) begin
                count <= count + 2'b01;
                addr0 <= 6'b000000;
            end
            else begin
                addr0 <= addr0 + 6'b000001;
            end
        end
    end
    
    always_comb begin
        if(count == 2'b10 && addr0 == 6'b111111) begin
            done = 1'b1;
        end
    end

endmodule

// counter/addresser for Convolution 2 layer output memory read (done)
module conv2_mem_read (input logic clk, reset, enable,
                        output logic [5:0] addr0, addr1, addr2, addr3,
                        output logic done);

    logic [1:0] count;
    always_ff @(posedge clk or posedge reset) begin
        if (reset == 1'b1) begin
            addr0 <= 6'b000000;
            addr1 <= 6'b000001;
            addr2 <= 6'b001000;
            addr3 <= 6'b001001;
            count <= 2'b00;
        end

        else if (enable == 1'b1 && done == 1'b0) begin
            if(count == 2'b11) begin
                count <= 2'b00;
                addr0 <= addr0 + 6'b001010;
                addr1 <= addr1 + 6'b001010;
                addr2 <= addr2 + 6'b001010;
                addr3 <= addr3 + 6'b001010;
            end
            else begin
                addr0 <= addr0 + 6'b000010;
                addr1 <= addr1 + 6'b000010;
                addr2 <= addr2 + 6'b000010;
                addr3 <= addr3 + 6'b000010;
                count <= count + 2'b01;
            end
        end
    end
    
    always_comb begin
        //stop when addr3 == 8^2 - 1, i.e. we have processed the entire image
        if(addr3 == 6'b111111) begin
            done = 1'b1;
        end
    end

endmodule

// counter/addresser for pooling 2 layer output memory write (done)
module P2_mem_write (input logic clk, reset, enable,
                        output logic [3:0] addr0,
                        output logic done);

    always_ff @(posedge clk or posedge reset) begin
        if (reset == 1'b1) begin
            addr0 <= 4'b0000;
        end
        else if (enable == 1'b1 && done == 1'b0) begin
            addr0 <= addr0 + 4'b0001;
        end
    end
    
    always_comb begin
        //stop when addr1 == 4^2 - 1, i.e. we have processed the entire image
        if(addr0 == 4'b1111) begin
            done = 1'b1;
        end
    end

endmodule

//cycle through 4x4 input images 12 times
// counter/addresser for pooling 2 layer output memory read
module P2_mem_read (input logic clk, reset, enable,
                        output logic [3:0] addr0,
                        output logic done);
    logic [3:0] count;

    always_ff @(posedge clk or posedge reset) begin
        if (reset == 1'b1) begin
            count <= 4'b0000;
            addr0 <= 4'b0000;
        end
        else if (enable == 1'b1 && done == 1'b0) begin
            if(addr0 == 4'b1111) begin
                count <= count + 4'b0001;
                addr0 <= 4'b0000;
            end
            else begin
                addr0 <= addr0 + 4'b0001;
            end
        end
    end

    always_comb begin
        if(count == 4'b1011 && addr0 == 4'b1111) begin
            done = 1'b1;
        end
    end

endmodule

// counter/addresser for Fully connected layer weight memory read (done)
module fc_mem_read (input logic clk, reset, enable, 
                        output logic [8:0] addr0, addr1, 
                        output logic done);

    always_ff @(posedge clk or posedge reset) begin
        if (reset == 1'b1) begin
            addr0 <= 9'b000000000;
            addr1 <= 9'b011000000;
        end
        else if (enable == 1'b1 && done == 1'b0) begin
            addr0 <= addr0 + 9'b000000001;
            addr1 <= addr1 + 9'b000000001;
        end
    end

    always_comb begin
        if(addr1 == 9'b101111111)
            done = 1'b1;
    end

endmodule

hardware/mem_counter_test/conv1_mem_write.vcd
$version Generated by VerilatedVcd $end
$date Thu May  5 10:30:43 2022
 $end
$timescale   1ns $end

 $scope module TOP $end
  $var wire 10 & addr0 [9:0] $end
  $var wire 10 ' addr1 [9:0] $end
  $var wire  1 # clk $end
  $var wire  1 ( done $end
  $var wire  1 % enable $end
  $var wire  1 $ reset $end
  $scope module conv1_mem_write $end
   $var wire 10 & addr0 [9:0] $end
   $var wire 10 ' addr1 [9:0] $end
   $var wire  1 # clk $end
   $var wire  1 ( done $end
   $var wire  1 % enable $end
   $var wire  1 $ reset $end
  $upscope $end
 $upscope $end
$enddefinitions $end


#0
0#
0$
0%
b0000000000 &
b0000000000 '
0(
#10
1#
#20
0#
1$
b0010010000 '
#30
1#
#40
0#
#50
1#
#60
0#
0$
#70
1#
#80
0#
1%
#90
1#
b0000000001 &
b0010010001 '
#100
0#
#110
1#
b0000000010 &
b0010010010 '
#120
0#
#130
1#
b0000000011 &
b0010010011 '
#140
0#
#150
1#
b0000000100 &
b0010010100 '
#160
0#
#170
1#
b0000000101 &
b0010010101 '
#180
0#
#190
1#
b0000000110 &
b0010010110 '
#200
0#
#210
1#
b0000000111 &
b0010010111 '
#220
0#
#230
1#
b0000001000 &
b0010011000 '
#240
0#
#250
1#
b0000001001 &
b0010011001 '
#260
0#
#270
1#
b0000001010 &
b0010011010 '
#280
0#
#290
1#
b0000001011 &
b0010011011 '
#300
0#
#310
1#
b0000001100 &
b0010011100 '
#320
0#
#330
1#
b0000001101 &
b0010011101 '
#340
0#
#350
1#
b0000001110 &
b0010011110 '
#360
0#
#370
1#
b0000001111 &
b0010011111 '
#380
0#
#390
1#
b0000010000 &
b0010100000 '
#400
0#
#410
1#
b0000010001 &
b0010100001 '
#420
0#
#430
1#
b0000010010 &
b0010100010 '
#440
0#
#450
1#
b0000010011 &
b0010100011 '
#460
0#
#470
1#
b0000010100 &
b0010100100 '
#480
0#
#490
1#
b0000010101 &
b0010100101 '
#500
0#
#510
1#
b0000010110 &
b0010100110 '
#520
0#
#530
1#
b0000010111 &
b0010100111 '
#540
0#
#550
1#
b0000011000 &
b0010101000 '
#560
0#
#570
1#
b0000011001 &
b0010101001 '
#580
0#
#590
1#
b0000011010 &
b0010101010 '
#600
0#
#610
1#
b0000011011 &
b0010101011 '
#620
0#
#630
1#
b0000011100 &
b0010101100 '
#640
0#
#650
1#
b0000011101 &
b0010101101 '
#660
0#
#670
1#
b0000011110 &
b0010101110 '
#680
0#
#690
1#
b0000011111 &
b0010101111 '
#700
0#
#710
1#
b0000100000 &
b0010110000 '
#720
0#
#730
1#
b0000100001 &
b0010110001 '
#740
0#
#750
1#
b0000100010 &
b0010110010 '
#760
0#
#770
1#
b0000100011 &
b0010110011 '
#780
0#
#790
1#
b0000100100 &
b0010110100 '
#800
0#
#810
1#
b0000100101 &
b0010110101 '
#820
0#
#830
1#
b0000100110 &
b0010110110 '
#840
0#
#850
1#
b0000100111 &
b0010110111 '
#860
0#
#870
1#
b0000101000 &
b0010111000 '
#880
0#
#890
1#
b0000101001 &
b0010111001 '
#900
0#
#910
1#
b0000101010 &
b0010111010 '
#920
0#
#930
1#
b0000101011 &
b0010111011 '
#940
0#
#950
1#
b0000101100 &
b0010111100 '
#960
0#
#970
1#
b0000101101 &
b0010111101 '
#980
0#
#990
1#
b0000101110 &
b0010111110 '
#1000
0#
#1010
1#
b0000101111 &
b0010111111 '
#1020
0#
#1030
1#
b0000110000 &
b0011000000 '
#1040
0#
#1050
1#
b0000110001 &
b0011000001 '
#1060
0#
#1070
1#
b0000110010 &
b0011000010 '
#1080
0#
#1090
1#
b0000110011 &
b0011000011 '
#1100
0#
#1110
1#
b0000110100 &
b0011000100 '
#1120
0#
#1130
1#
b0000110101 &
b0011000101 '
#1140
0#
#1150
1#
b0000110110 &
b0011000110 '
#1160
0#
#1170
1#
b0000110111 &
b0011000111 '
#1180
0#
#1190
1#
b0000111000 &
b0011001000 '
#1200
0#
#1210
1#
b0000111001 &
b0011001001 '
#1220
0#
#1230
1#
b0000111010 &
b0011001010 '
#1240
0#
#1250
1#
b0000111011 &
b0011001011 '
#1260
0#
#1270
1#
b0000111100 &
b0011001100 '
#1280
0#
#1290
1#
b0000111101 &
b0011001101 '
#1300
0#
#1310
1#
b0000111110 &
b0011001110 '
#1320
0#
#1330
1#
b0000111111 &
b0011001111 '
#1340
0#
#1350
1#
b0001000000 &
b0011010000 '
#1360
0#
#1370
1#
b0001000001 &
b0011010001 '
#1380
0#
#1390
1#
b0001000010 &
b0011010010 '
#1400
0#
#1410
1#
b0001000011 &
b0011010011 '
#1420
0#
#1430
1#
b0001000100 &
b0011010100 '
#1440
0#
#1450
1#
b0001000101 &
b0011010101 '
#1460
0#
#1470
1#
b0001000110 &
b0011010110 '
#1480
0#
#1490
1#
b0001000111 &
b0011010111 '
#1500
0#
#1510
1#
b0001001000 &
b0011011000 '
#1520
0#
#1530
1#
b0001001001 &
b0011011001 '
#1540
0#
#1550
1#
b0001001010 &
b0011011010 '
#1560
0#
#1570
1#
b0001001011 &
b0011011011 '
#1580
0#
#1590
1#
b0001001100 &
b0011011100 '
#1600
0#
#1610
1#
b0001001101 &
b0011011101 '
#1620
0#
#1630
1#
b0001001110 &
b0011011110 '
#1640
0#
#1650
1#
b0001001111 &
b0011011111 '
#1660
0#
#1670
1#
b0001010000 &
b0011100000 '
#1680
0#
#1690
1#
b0001010001 &
b0011100001 '
#1700
0#
#1710
1#
b0001010010 &
b0011100010 '
#1720
0#
#1730
1#
b0001010011 &
b0011100011 '
#1740
0#
#1750
1#
b0001010100 &
b0011100100 '
#1760
0#
#1770
1#
b0001010101 &
b0011100101 '
#1780
0#
#1790
1#
b0001010110 &
b0011100110 '
#1800
0#
#1810
1#
b0001010111 &
b0011100111 '
#1820
0#
#1830
1#
b0001011000 &
b0011101000 '
#1840
0#
#1850
1#
b0001011001 &
b0011101001 '
#1860
0#
#1870
1#
b0001011010 &
b0011101010 '
#1880
0#
#1890
1#
b0001011011 &
b0011101011 '
#1900
0#
#1910
1#
b0001011100 &
b0011101100 '
#1920
0#
#1930
1#
b0001011101 &
b0011101101 '
#1940
0#
#1950
1#
b0001011110 &
b0011101110 '
#1960
0#
#1970
1#
b0001011111 &
b0011101111 '
#1980
0#
#1990
1#
b0001100000 &
b0011110000 '
#2000
0#
#2010
1#
b0001100001 &
b0011110001 '
#2020
0#
#2030
1#
b0001100010 &
b0011110010 '
#2040
0#
#2050
1#
b0001100011 &
b0011110011 '
#2060
0#
#2070
1#
b0001100100 &
b0011110100 '
#2080
0#
#2090
1#
b0001100101 &
b0011110101 '
#2100
0#
#2110
1#
b0001100110 &
b0011110110 '
#2120
0#
#2130
1#
b0001100111 &
b0011110111 '
#2140
0#
#2150
1#
b0001101000 &
b0011111000 '
#2160
0#
#2170
1#
b0001101001 &
b0011111001 '
#2180
0#
#2190
1#
b0001101010 &
b0011111010 '
#2200
0#
#2210
1#
b0001101011 &
b0011111011 '
#2220
0#
#2230
1#
b0001101100 &
b0011111100 '
#2240
0#
#2250
1#
b0001101101 &
b0011111101 '
#2260
0#
#2270
1#
b0001101110 &
b0011111110 '
#2280
0#
#2290
1#
b0001101111 &
b0011111111 '
#2300
0#
#2310
1#
b0001110000 &
b0100000000 '
#2320
0#
#2330
1#
b0001110001 &
b0100000001 '
#2340
0#
#2350
1#
b0001110010 &
b0100000010 '
#2360
0#
#2370
1#
b0001110011 &
b0100000011 '
#2380
0#
#2390
1#
b0001110100 &
b0100000100 '
#2400
0#
#2410
1#
b0001110101 &
b0100000101 '
#2420
0#
#2430
1#
b0001110110 &
b0100000110 '
#2440
0#
#2450
1#
b0001110111 &
b0100000111 '
#2460
0#
#2470
1#
b0001111000 &
b0100001000 '
#2480
0#
#2490
1#
b0001111001 &
b0100001001 '
#2500
0#
#2510
1#
b0001111010 &
b0100001010 '
#2520
0#
#2530
1#
b0001111011 &
b0100001011 '
#2540
0#
#2550
1#
b0001111100 &
b0100001100 '
#2560
0#
#2570
1#
b0001111101 &
b0100001101 '
#2580
0#
#2590
1#
b0001111110 &
b0100001110 '
#2600
0#
#2610
1#
b0001111111 &
b0100001111 '
#2620
0#
#2630
1#
b0010000000 &
b0100010000 '
#2640
0#
#2650
1#
b0010000001 &
b0100010001 '
#2660
0#
#2670
1#
b0010000010 &
b0100010010 '
#2680
0#
#2690
1#
b0010000011 &
b0100010011 '
#2700
0#
#2710
1#
b0010000100 &
b0100010100 '
#2720
0#
#2730
1#
b0010000101 &
b0100010101 '
#2740
0#
#2750
1#
b0010000110 &
b0100010110 '
#2760
0#
#2770
1#
b0010000111 &
b0100010111 '
#2780
0#
#2790
1#
b0010001000 &
b0100011000 '
#2800
0#
#2810
1#
b0010001001 &
b0100011001 '
#2820
0#
#2830
1#
b0010001010 &
b0100011010 '
#2840
0#
#2850
1#
b0010001011 &
b0100011011 '
#2860
0#
#2870
1#
b0010001100 &
b0100011100 '
#2880
0#
#2890
1#
b0010001101 &
b0100011101 '
#2900
0#
#2910
1#
b0010001110 &
b0100011110 '
#2920
0#
#2930
1#
b0010001111 &
b0100011111 '
#2940
0#
#2950
1#
b0010010000 &
b0100100000 '
#2960
0#
#2970
1#
b0010010001 &
b0100100001 '
#2980
0#
#2990
1#
b0010010010 &
b0100100010 '
#3000
0#
#3010
1#
b0010010011 &
b0100100011 '
#3020
0#
#3030
1#
b0010010100 &
b0100100100 '
#3040
0#
#3050
1#
b0010010101 &
b0100100101 '
#3060
0#
#3070
1#
b0010010110 &
b0100100110 '
#3080
0#
#3090
1#
b0010010111 &
b0100100111 '
#3100
0#
#3110
1#
b0010011000 &
b0100101000 '
#3120
0#
#3130
1#
b0010011001 &
b0100101001 '
#3140
0#
#3150
1#
b0010011010 &
b0100101010 '
#3160
0#
#3170
1#
b0010011011 &
b0100101011 '
#3180
0#
#3190
1#
b0010011100 &
b0100101100 '
#3200
0#
#3210
1#
b0010011101 &
b0100101101 '
#3220
0#
#3230
1#
b0010011110 &
b0100101110 '
#3240
0#
#3250
1#
b0010011111 &
b0100101111 '
#3260
0#
#3270
1#
b0010100000 &
b0100110000 '
#3280
0#
#3290
1#
b0010100001 &
b0100110001 '
#3300
0#
#3310
1#
b0010100010 &
b0100110010 '
#3320
0#
#3330
1#
b0010100011 &
b0100110011 '
#3340
0#
#3350
1#
b0010100100 &
b0100110100 '
#3360
0#
#3370
1#
b0010100101 &
b0100110101 '
#3380
0#
#3390
1#
b0010100110 &
b0100110110 '
#3400
0#
#3410
1#
b0010100111 &
b0100110111 '
#3420
0#
#3430
1#
b0010101000 &
b0100111000 '
#3440
0#
#3450
1#
b0010101001 &
b0100111001 '
#3460
0#
#3470
1#
b0010101010 &
b0100111010 '
#3480
0#
#3490
1#
b0010101011 &
b0100111011 '
#3500
0#
#3510
1#
b0010101100 &
b0100111100 '
#3520
0#
#3530
1#
b0010101101 &
b0100111101 '
#3540
0#
#3550
1#
b0010101110 &
b0100111110 '
#3560
0#
#3570
1#
b0010101111 &
b0100111111 '
#3580
0#
#3590
1#
b0010110000 &
b0101000000 '
#3600
0#
#3610
1#
b0010110001 &
b0101000001 '
#3620
0#
#3630
1#
b0010110010 &
b0101000010 '
#3640
0#
#3650
1#
b0010110011 &
b0101000011 '
#3660
0#
#3670
1#
b0010110100 &
b0101000100 '
#3680
0#
#3690
1#
b0010110101 &
b0101000101 '
#3700
0#
#3710
1#
b0010110110 &
b0101000110 '
#3720
0#
#3730
1#
b0010110111 &
b0101000111 '
#3740
0#
#3750
1#
b0010111000 &
b0101001000 '
#3760
0#
#3770
1#
b0010111001 &
b0101001001 '
#3780
0#
#3790
1#
b0010111010 &
b0101001010 '
#3800
0#
#3810
1#
b0010111011 &
b0101001011 '
#3820
0#
#3830
1#
b0010111100 &
b0101001100 '
#3840
0#
#3850
1#
b0010111101 &
b0101001101 '
#3860
0#
#3870
1#
b0010111110 &
b0101001110 '
#3880
0#
#3890
1#
b0010111111 &
b0101001111 '
#3900
0#
#3910
1#
b0011000000 &
b0101010000 '
#3920
0#
#3930
1#
b0011000001 &
b0101010001 '
#3940
0#
#3950
1#
b0011000010 &
b0101010010 '
#3960
0#
#3970
1#
b0011000011 &
b0101010011 '
#3980
0#
#3990
1#
b0011000100 &
b0101010100 '
#4000
0#
#4010
1#
b0011000101 &
b0101010101 '
#4020
0#
#4030
1#
b0011000110 &
b0101010110 '
#4040
0#
#4050
1#
b0011000111 &
b0101010111 '
#4060
0#
#4070
1#
b0011001000 &
b0101011000 '
#4080
0#
#4090
1#
b0011001001 &
b0101011001 '
#4100
0#
#4110
1#
b0011001010 &
b0101011010 '
#4120
0#
#4130
1#
b0011001011 &
b0101011011 '
#4140
0#
#4150
1#
b0011001100 &
b0101011100 '
#4160
0#
#4170
1#
b0011001101 &
b0101011101 '
#4180
0#
#4190
1#
b0011001110 &
b0101011110 '
#4200
0#
#4210
1#
b0011001111 &
b0101011111 '
#4220
0#
#4230
1#
b0011010000 &
b0101100000 '
#4240
0#
#4250
1#
b0011010001 &
b0101100001 '
#4260
0#
#4270
1#
b0011010010 &
b0101100010 '
#4280
0#
#4290
1#
b0011010011 &
b0101100011 '
#4300
0#
#4310
1#
b0011010100 &
b0101100100 '
#4320
0#
#4330
1#
b0011010101 &
b0101100101 '
#4340
0#
#4350
1#
b0011010110 &
b0101100110 '
#4360
0#
#4370
1#
b0011010111 &
b0101100111 '
#4380
0#
#4390
1#
b0011011000 &
b0101101000 '
#4400
0#
#4410
1#
b0011011001 &
b0101101001 '
#4420
0#
#4430
1#
b0011011010 &
b0101101010 '
#4440
0#
#4450
1#
b0011011011 &
b0101101011 '
#4460
0#
#4470
1#
b0011011100 &
b0101101100 '
#4480
0#
#4490
1#
b0011011101 &
b0101101101 '
#4500
0#
#4510
1#
b0011011110 &
b0101101110 '
#4520
0#
#4530
1#
b0011011111 &
b0101101111 '
#4540
0#
#4550
1#
b0011100000 &
b0101110000 '
#4560
0#
#4570
1#
b0011100001 &
b0101110001 '
#4580
0#
#4590
1#
b0011100010 &
b0101110010 '
#4600
0#
#4610
1#
b0011100011 &
b0101110011 '
#4620
0#
#4630
1#
b0011100100 &
b0101110100 '
#4640
0#
#4650
1#
b0011100101 &
b0101110101 '
#4660
0#
#4670
1#
b0011100110 &
b0101110110 '
#4680
0#
#4690
1#
b0011100111 &
b0101110111 '
#4700
0#
#4710
1#
b0011101000 &
b0101111000 '
#4720
0#
#4730
1#
b0011101001 &
b0101111001 '
#4740
0#
#4750
1#
b0011101010 &
b0101111010 '
#4760
0#
#4770
1#
b0011101011 &
b0101111011 '
#4780
0#
#4790
1#
b0011101100 &
b0101111100 '
#4800
0#
#4810
1#
b0011101101 &
b0101111101 '
#4820
0#
#4830
1#
b0011101110 &
b0101111110 '
#4840
0#
#4850
1#
b0011101111 &
b0101111111 '
#4860
0#
#4870
1#
b0011110000 &
b0110000000 '
#4880
0#
#4890
1#
b0011110001 &
b0110000001 '
#4900
0#
#4910
1#
b0011110010 &
b0110000010 '
#4920
0#
#4930
1#
b0011110011 &
b0110000011 '
#4940
0#
#4950
1#
b0011110100 &
b0110000100 '
#4960
0#
#4970
1#
b0011110101 &
b0110000101 '
#4980
0#
#4990
1#
b0011110110 &
b0110000110 '
#5000
0#
#5010
1#
b0011110111 &
b0110000111 '
#5020
0#
#5030
1#
b0011111000 &
b0110001000 '
#5040
0#
#5050
1#
b0011111001 &
b0110001001 '
#5060
0#
#5070
1#
b0011111010 &
b0110001010 '
#5080
0#
#5090
1#
b0011111011 &
b0110001011 '
#5100
0#
#5110
1#
b0011111100 &
b0110001100 '
#5120
0#
#5130
1#
b0011111101 &
b0110001101 '
#5140
0#
#5150
1#
b0011111110 &
b0110001110 '
#5160
0#
#5170
1#
b0011111111 &
b0110001111 '
#5180
0#
#5190
1#
b0100000000 &
b0110010000 '
#5200
0#
#5210
1#
b0100000001 &
b0110010001 '
#5220
0#
#5230
1#
b0100000010 &
b0110010010 '
#5240
0#
#5250
1#
b0100000011 &
b0110010011 '
#5260
0#
#5270
1#
b0100000100 &
b0110010100 '
#5280
0#
#5290
1#
b0100000101 &
b0110010101 '
#5300
0#
#5310
1#
b0100000110 &
b0110010110 '
#5320
0#
#5330
1#
b0100000111 &
b0110010111 '
#5340
0#
#5350
1#
b0100001000 &
b0110011000 '
#5360
0#
#5370
1#
b0100001001 &
b0110011001 '
#5380
0#
#5390
1#
b0100001010 &
b0110011010 '
#5400
0#
#5410
1#
b0100001011 &
b0110011011 '
#5420
0#
#5430
1#
b0100001100 &
b0110011100 '
#5440
0#
#5450
1#
b0100001101 &
b0110011101 '
#5460
0#
#5470
1#
b0100001110 &
b0110011110 '
#5480
0#
#5490
1#
b0100001111 &
b0110011111 '
#5500
0#
#5510
1#
b0100010000 &
b0110100000 '
#5520
0#
#5530
1#
b0100010001 &
b0110100001 '
#5540
0#
#5550
1#
b0100010010 &
b0110100010 '
#5560
0#
#5570
1#
b0100010011 &
b0110100011 '
#5580
0#
#5590
1#
b0100010100 &
b0110100100 '
#5600
0#
#5610
1#
b0100010101 &
b0110100101 '
#5620
0#
#5630
1#
b0100010110 &
b0110100110 '
#5640
0#
#5650
1#
b0100010111 &
b0110100111 '
#5660
0#
#5670
1#
b0100011000 &
b0110101000 '
#5680
0#
#5690
1#
b0100011001 &
b0110101001 '
#5700
0#
#5710
1#
b0100011010 &
b0110101010 '
#5720
0#
#5730
1#
b0100011011 &
b0110101011 '
#5740
0#
#5750
1#
b0100011100 &
b0110101100 '
#5760
0#
#5770
1#
b0100011101 &
b0110101101 '
#5780
0#
#5790
1#
b0100011110 &
b0110101110 '
#5800
0#
#5810
1#
b0100011111 &
b0110101111 '
#5820
0#
#5830
1#
b0100100000 &
b0110110000 '
#5840
0#
#5850
1#
b0100100001 &
b0110110001 '
#5860
0#
#5870
1#
b0100100010 &
b0110110010 '
#5880
0#
#5890
1#
b0100100011 &
b0110110011 '
#5900
0#
