hardware/mem_counter_test/conv1_mem_read.sv
// counter/addresser for Convolution 1 layer output memory read (done?)
module conv1_mem_read (input logic clk, reset, enable,
                        output logic [9:0] addr0, addr1, addr2, addr3, 
                        output logic done);

    logic [3:0] count;
    always_ff @(posedge clk or posedge reset) begin
        if (reset == 1'b1) begin
            addr0 <= 10'b0000000000;
            addr1 <= 10'b0000000001;
            addr2 <= 10'b0000011000;
            addr3 <= 10'b0000011001;
            count <= 4'b0000;
        end
        
        else if (enable == 1'b1 && done == 1'b0) begin
            if(count == 4'b1011) begin
                count <= 4'b0000;
                addr0 <= addr0 + 10'b0000011010;
                addr1 <= addr1 + 10'b0000011010;
                addr2 <= addr2 + 10'b0000011010;
                addr3 <= addr3 + 10'b0000011010;
            end
            else begin    
                addr0 <= addr0 + 10'b0000000010;
                addr1 <= addr1 + 10'b0000000010;
                addr2 <= addr2 + 10'b0000000010;
                addr3 <= addr3 + 10'b0000000010;
                count <= count + 4'b0001;
            end
        end
    end
    
    always_comb begin
        //stop when addr3 == 24^2 - 1, i.e. we have processed the entire image
        if(addr3 == 10'b1000111111) begin
            done = 1'b1;
        end
    end

endmodule

hardware/mem_counter_test/conv1_mem_read.vcd
$version Generated by VerilatedVcd $end
$date Thu May  5 10:30:32 2022
 $end
$timescale   1ns $end

 $scope module TOP $end
  $var wire 10 ' addr0 [9:0] $end
  $var wire 10 ( addr1 [9:0] $end
  $var wire 10 ) addr2 [9:0] $end
  $var wire 10 * addr3 [9:0] $end
  $var wire  1 $ clk $end
  $var wire  1 + done $end
  $var wire  1 & enable $end
  $var wire  1 % reset $end
  $scope module conv1_mem_read $end
   $var wire 10 ' addr0 [9:0] $end
   $var wire 10 ( addr1 [9:0] $end
   $var wire 10 ) addr2 [9:0] $end
   $var wire 10 * addr3 [9:0] $end
   $var wire  1 $ clk $end
   $var wire  4 # count [3:0] $end
   $var wire  1 + done $end
   $var wire  1 & enable $end
   $var wire  1 % reset $end
  $upscope $end
 $upscope $end
$enddefinitions $end


#0
b0000 #
0$
0%
0&
b0000000000 '
b0000000000 (
b0000000000 )
b0000000000 *
0+
#10
1$
#20
0$
1%
b0000000001 (
b0000011000 )
b0000011001 *
#30
1$
#40
0$
#50
1$
#60
0$
0%
#70
1$
#80
0$
1&
#90
b0001 #
1$
b0000000010 '
b0000000011 (
b0000011010 )
b0000011011 *
#100
0$
#110
b0010 #
1$
b0000000100 '
b0000000101 (
b0000011100 )
b0000011101 *
#120
0$
#130
b0011 #
1$
b0000000110 '
b0000000111 (
b0000011110 )
b0000011111 *
#140
0$
#150
b0100 #
1$
b0000001000 '
b0000001001 (
b0000100000 )
b0000100001 *
#160
0$
#170
b0101 #
1$
b0000001010 '
b0000001011 (
b0000100010 )
b0000100011 *
#180
0$
#190
b0110 #
1$
b0000001100 '
b0000001101 (
b0000100100 )
b0000100101 *
#200
0$
#210
b0111 #
1$
b0000001110 '
b0000001111 (
b0000100110 )
b0000100111 *
#220
0$
#230
b1000 #
1$
b0000010000 '
b0000010001 (
b0000101000 )
b0000101001 *
#240
0$
#250
b1001 #
1$
b0000010010 '
b0000010011 (
b0000101010 )
b0000101011 *
#260
0$
#270
b1010 #
1$
b0000010100 '
b0000010101 (
b0000101100 )
b0000101101 *
#280
0$
#290
b1011 #
1$
b0000010110 '
b0000010111 (
b0000101110 )
b0000101111 *
#300
0$
#310
b0000 #
1$
b0000110000 '
b0000110001 (
b0001001000 )
b0001001001 *
#320
0$
#330
b0001 #
1$
b0000110010 '
b0000110011 (
b0001001010 )
b0001001011 *
#340
0$
#350
b0010 #
1$
b0000110100 '
b0000110101 (
b0001001100 )
b0001001101 *
#360
0$
#370
b0011 #
1$
b0000110110 '
b0000110111 (
b0001001110 )
b0001001111 *
#380
0$
#390
b0100 #
1$
b0000111000 '
b0000111001 (
b0001010000 )
b0001010001 *
#400
0$
#410
b0101 #
1$
b0000111010 '
b0000111011 (
b0001010010 )
b0001010011 *
#420
0$
#430
b0110 #
1$
b0000111100 '
b0000111101 (
b0001010100 )
b0001010101 *
#440
0$
#450
b0111 #
1$
b0000111110 '
b0000111111 (
b0001010110 )
b0001010111 *
#460
0$
#470
b1000 #
1$
b0001000000 '
b0001000001 (
b0001011000 )
b0001011001 *
#480
0$
#490
b1001 #
1$
b0001000010 '
b0001000011 (
b0001011010 )
b0001011011 *
#500
0$
#510
b1010 #
1$
b0001000100 '
b0001000101 (
b0001011100 )
b0001011101 *
#520
0$
#530
b1011 #
1$
b0001000110 '
b0001000111 (
b0001011110 )
b0001011111 *
#540
0$
#550
b0000 #
1$
b0001100000 '
b0001100001 (
b0001111000 )
b0001111001 *
#560
0$
#570
b0001 #
1$
b0001100010 '
b0001100011 (
b0001111010 )
b0001111011 *
#580
0$
#590
b0010 #
1$
b0001100100 '
b0001100101 (
b0001111100 )
b0001111101 *
#600
0$
#610
b0011 #
1$
b0001100110 '
b0001100111 (
b0001111110 )
b0001111111 *
#620
0$
#630
b0100 #
1$
b0001101000 '
b0001101001 (
b0010000000 )
b0010000001 *
#640
0$
#650
b0101 #
1$
b0001101010 '
b0001101011 (
b0010000010 )
b0010000011 *
#660
0$
#670
b0110 #
1$
b0001101100 '
b0001101101 (
b0010000100 )
b0010000101 *
#680
0$
#690
b0111 #
1$
b0001101110 '
b0001101111 (
b0010000110 )
b0010000111 *
#700
0$
#710
b1000 #
1$
b0001110000 '
b0001110001 (
b0010001000 )
b0010001001 *
#720
0$
#730
b1001 #
1$
b0001110010 '
b0001110011 (
b0010001010 )
b0010001011 *
#740
0$
#750
b1010 #
1$
b0001110100 '
b0001110101 (
b0010001100 )
b0010001101 *
#760
0$
#770
b1011 #
1$
b0001110110 '
b0001110111 (
b0010001110 )
b0010001111 *
#780
0$
#790
b0000 #
1$
b0010010000 '
b0010010001 (
b0010101000 )
b0010101001 *
#800
0$
#810
b0001 #
1$
b0010010010 '
b0010010011 (
b0010101010 )
b0010101011 *
#820
0$
#830
b0010 #
1$
b0010010100 '
b0010010101 (
b0010101100 )
b0010101101 *
#840
0$
#850
b0011 #
1$
b0010010110 '
b0010010111 (
b0010101110 )
b0010101111 *
#860
0$
#870
b0100 #
1$
b0010011000 '
b0010011001 (
b0010110000 )
b0010110001 *
#880
0$
#890
b0101 #
1$
b0010011010 '
b0010011011 (
b0010110010 )
b0010110011 *
#900
0$
#910
b0110 #
1$
b0010011100 '
b0010011101 (
b0010110100 )
b0010110101 *
#920
0$
#930
b0111 #
1$
b0010011110 '
b0010011111 (
b0010110110 )
b0010110111 *
#940
0$
#950
b1000 #
1$
b0010100000 '
b0010100001 (
b0010111000 )
b0010111001 *
#960
0$
#970
b1001 #
1$
b0010100010 '
b0010100011 (
b0010111010 )
b0010111011 *
#980
0$
#990
b1010 #
1$
b0010100100 '
b0010100101 (
b0010111100 )
b0010111101 *
#1000
0$
#1010
b1011 #
1$
b0010100110 '
b0010100111 (
b0010111110 )
b0010111111 *
#1020
0$
#1030
b0000 #
1$
b0011000000 '
b0011000001 (
b0011011000 )
b0011011001 *
#1040
0$
#1050
b0001 #
1$
b0011000010 '
b0011000011 (
b0011011010 )
b0011011011 *
#1060
0$
#1070
b0010 #
1$
b0011000100 '
b0011000101 (
b0011011100 )
b0011011101 *
#1080
0$
#1090
b0011 #
1$
b0011000110 '
b0011000111 (
b0011011110 )
b0011011111 *
#1100
0$
#1110
b0100 #
1$
b0011001000 '
b0011001001 (
b0011100000 )
b0011100001 *
#1120
0$
#1130
b0101 #
1$
b0011001010 '
b0011001011 (
b0011100010 )
b0011100011 *
#1140
0$
#1150
b0110 #
1$
b0011001100 '
b0011001101 (
b0011100100 )
b0011100101 *
#1160
0$
#1170
b0111 #
1$
b0011001110 '
b0011001111 (
b0011100110 )
b0011100111 *
#1180
0$
#1190
b1000 #
1$
b0011010000 '
b0011010001 (
b0011101000 )
b0011101001 *
#1200
0$
#1210
b1001 #
1$
b0011010010 '
b0011010011 (
b0011101010 )
b0011101011 *
#1220
0$
#1230
b1010 #
1$
b0011010100 '
b0011010101 (
b0011101100 )
b0011101101 *
#1240
0$
#1250
b1011 #
1$
b0011010110 '
b0011010111 (
b0011101110 )
b0011101111 *
#1260
0$
#1270
b0000 #
1$
b0011110000 '
b0011110001 (
b0100001000 )
b0100001001 *
#1280
0$
#1290
b0001 #
1$
b0011110010 '
b0011110011 (
b0100001010 )
b0100001011 *
#1300
0$
#1310
b0010 #
1$
b0011110100 '
b0011110101 (
b0100001100 )
b0100001101 *
#1320
0$
#1330
b0011 #
1$
b0011110110 '
b0011110111 (
b0100001110 )
b0100001111 *
#1340
0$
#1350
b0100 #
1$
b0011111000 '
b0011111001 (
b0100010000 )
b0100010001 *
#1360
0$
#1370
b0101 #
1$
b0011111010 '
b0011111011 (
b0100010010 )
b0100010011 *
#1380
0$
#1390
b0110 #
1$
b0011111100 '
b0011111101 (
b0100010100 )
b0100010101 *
#1400
0$
#1410
b0111 #
1$
b0011111110 '
b0011111111 (
b0100010110 )
b0100010111 *
#1420
0$
#1430
b1000 #
1$
b0100000000 '
b0100000001 (
b0100011000 )
b0100011001 *
#1440
0$
#1450
b1001 #
1$
b0100000010 '
b0100000011 (
b0100011010 )
b0100011011 *
#1460
0$
#1470
b1010 #
1$
b0100000100 '
b0100000101 (
b0100011100 )
b0100011101 *
#1480
0$
#1490
b1011 #
1$
b0100000110 '
b0100000111 (
b0100011110 )
b0100011111 *
#1500
0$
#1510
b0000 #
1$
b0100100000 '
b0100100001 (
b0100111000 )
b0100111001 *
#1520
0$
#1530
b0001 #
1$
b0100100010 '
b0100100011 (
b0100111010 )
b0100111011 *
#1540
0$
#1550
b0010 #
1$
b0100100100 '
b0100100101 (
b0100111100 )
b0100111101 *
#1560
0$
#1570
b0011 #
1$
b0100100110 '
b0100100111 (
b0100111110 )
b0100111111 *
#1580
0$
#1590
b0100 #
1$
b0100101000 '
b0100101001 (
b0101000000 )
b0101000001 *
#1600
0$
#1610
b0101 #
1$
b0100101010 '
b0100101011 (
b0101000010 )
b0101000011 *
#1620
0$
#1630
b0110 #
1$
b0100101100 '
b0100101101 (
b0101000100 )
b0101000101 *
#1640
0$
#1650
b0111 #
1$
b0100101110 '
b0100101111 (
b0101000110 )
b0101000111 *
#1660
0$
#1670
b1000 #
1$
b0100110000 '
b0100110001 (
b0101001000 )
b0101001001 *
#1680
0$
#1690
b1001 #
1$
b0100110010 '
b0100110011 (
b0101001010 )
b0101001011 *
#1700
0$
#1710
b1010 #
1$
b0100110100 '
b0100110101 (
b0101001100 )
b0101001101 *
#1720
0$
#1730
b1011 #
1$
b0100110110 '
b0100110111 (
b0101001110 )
b0101001111 *
#1740
0$
#1750
b0000 #
1$
b0101010000 '
b0101010001 (
b0101101000 )
b0101101001 *
#1760
0$
#1770
b0001 #
1$
b0101010010 '
b0101010011 (
b0101101010 )
b0101101011 *
#1780
0$
#1790
b0010 #
1$
b0101010100 '
b0101010101 (
b0101101100 )
b0101101101 *
#1800
0$
#1810
b0011 #
1$
b0101010110 '
b0101010111 (
b0101101110 )
b0101101111 *
#1820
0$
#1830
b0100 #
1$
b0101011000 '
b0101011001 (
b0101110000 )
b0101110001 *
#1840
0$
#1850
b0101 #
1$
b0101011010 '
b0101011011 (
b0101110010 )
b0101110011 *
#1860
0$
#1870
b0110 #
1$
b0101011100 '
b0101011101 (
b0101110100 )
b0101110101 *
#1880
0$
#1890
b0111 #
1$
b0101011110 '
b0101011111 (
b0101110110 )
b0101110111 *
#1900
0$
#1910
b1000 #
1$
b0101100000 '
b0101100001 (
b0101111000 )
b0101111001 *
#1920
0$
#1930
b1001 #
1$
b0101100010 '
b0101100011 (
b0101111010 )
b0101111011 *
#1940
0$
#1950
b1010 #
1$
b0101100100 '
b0101100101 (
b0101111100 )
b0101111101 *
#1960
0$
#1970
b1011 #
1$
b0101100110 '
b0101100111 (
b0101111110 )
b0101111111 *
#1980
0$
#1990
b0000 #
1$
b0110000000 '
b0110000001 (
b0110011000 )
b0110011001 *
#2000
0$
#2010
b0001 #
1$
b0110000010 '
b0110000011 (
b0110011010 )
b0110011011 *
#2020
0$
#2030
b0010 #
1$
b0110000100 '
b0110000101 (
b0110011100 )
b0110011101 *
#2040
0$
#2050
b0011 #
1$
b0110000110 '
b0110000111 (
b0110011110 )
b0110011111 *
#2060
0$
#2070
b0100 #
1$
b0110001000 '
b0110001001 (
b0110100000 )
b0110100001 *
#2080
0$
#2090
b0101 #
1$
b0110001010 '
b0110001011 (
b0110100010 )
b0110100011 *
#2100
0$
#2110
b0110 #
1$
b0110001100 '
b0110001101 (
b0110100100 )
b0110100101 *
#2120
0$
#2130
b0111 #
1$
b0110001110 '
b0110001111 (
b0110100110 )
b0110100111 *
#2140
0$
#2150
b1000 #
1$
b0110010000 '
b0110010001 (
b0110101000 )
b0110101001 *
#2160
0$
#2170
b1001 #
1$
b0110010010 '
b0110010011 (
b0110101010 )
b0110101011 *
#2180
0$
#2190
b1010 #
1$
b0110010100 '
b0110010101 (
b0110101100 )
b0110101101 *
#2200
0$
#2210
b1011 #
1$
b0110010110 '
b0110010111 (
b0110101110 )
b0110101111 *
#2220
0$
#2230
b0000 #
1$
b0110110000 '
b0110110001 (
b0111001000 )
b0111001001 *
#2240
0$
#2250
b0001 #
1$
b0110110010 '
b0110110011 (
b0111001010 )
b0111001011 *
#2260
0$
#2270
b0010 #
1$
b0110110100 '
b0110110101 (
b0111001100 )
b0111001101 *
#2280
0$
#2290
b0011 #
1$
b0110110110 '
b0110110111 (
b0111001110 )
b0111001111 *
#2300
0$
#2310
b0100 #
1$
b0110111000 '
b0110111001 (
b0111010000 )
b0111010001 *
#2320
0$
#2330
b0101 #
1$
b0110111010 '
b0110111011 (
b0111010010 )
b0111010011 *
#2340
0$
#2350
b0110 #
1$
b0110111100 '
b0110111101 (
b0111010100 )
b0111010101 *
#2360
0$
#2370
b0111 #
1$
b0110111110 '
b0110111111 (
b0111010110 )
b0111010111 *
#2380
0$
#2390
b1000 #
1$
b0111000000 '
b0111000001 (
b0111011000 )
b0111011001 *
#2400
0$
#2410
b1001 #
1$
b0111000010 '
b0111000011 (
b0111011010 )
b0111011011 *
#2420
0$
#2430
b1010 #
1$
b0111000100 '
b0111000101 (
b0111011100 )
b0111011101 *
#2440
0$
#2450
b1011 #
1$
b0111000110 '
b0111000111 (
b0111011110 )
b0111011111 *
#2460
0$
#2470
b0000 #
1$
b0111100000 '
b0111100001 (
b0111111000 )
b0111111001 *
#2480
0$
#2490
b0001 #
1$
b0111100010 '
b0111100011 (
b0111111010 )
b0111111011 *
#2500
0$
#2510
b0010 #
1$
b0111100100 '
b0111100101 (
b0111111100 )
b0111111101 *
#2520
0$
#2530
b0011 #
1$
b0111100110 '
b0111100111 (
b0111111110 )
b0111111111 *
#2540
0$
#2550
b0100 #
1$
b0111101000 '
b0111101001 (
b1000000000 )
b1000000001 *
#2560
0$
#2570
b0101 #
1$
b0111101010 '
b0111101011 (
b1000000010 )
b1000000011 *
#2580
0$
#2590
b0110 #
1$
b0111101100 '
b0111101101 (
b1000000100 )
b1000000101 *
#2600
0$
#2610
b0111 #
1$
b0111101110 '
b0111101111 (
b1000000110 )
b1000000111 *
#2620
0$
#2630
b1000 #
1$
b0111110000 '
b0111110001 (
b1000001000 )
b1000001001 *
#2640
0$
#2650
b1001 #
1$
b0111110010 '
b0111110011 (
b1000001010 )
b1000001011 *
#2660
0$
#2670
b1010 #
1$
b0111110100 '
b0111110101 (
b1000001100 )
b1000001101 *
#2680
0$
#2690
b1011 #
1$
b0111110110 '
b0111110111 (
b1000001110 )
b1000001111 *
#2700
0$
#2710
b0000 #
1$
b1000010000 '
b1000010001 (
b1000101000 )
b1000101001 *
#2720
0$
#2730
b0001 #
1$
b1000010010 '
b1000010011 (
b1000101010 )
b1000101011 *
#2740
0$
#2750
b0010 #
1$
b1000010100 '
b1000010101 (
b1000101100 )
b1000101101 *
#2760
0$
#2770
b0011 #
1$
b1000010110 '
b1000010111 (
b1000101110 )
b1000101111 *
#2780
0$
#2790
b0100 #
1$
b1000011000 '
b1000011001 (
b1000110000 )
b1000110001 *
#2800
0$
#2810
b0101 #
1$
b1000011010 '
b1000011011 (
b1000110010 )
b1000110011 *
#2820
0$
#2830
b0110 #
1$
b1000011100 '
b1000011101 (
b1000110100 )
b1000110101 *
#2840
0$
#2850
b0111 #
1$
b1000011110 '
b1000011111 (
b1000110110 )
b1000110111 *
#2860
0$
#2870
b1000 #
1$
b1000100000 '
b1000100001 (
b1000111000 )
b1000111001 *
#2880
0$
#2890
b1001 #
1$
b1000100010 '
b1000100011 (
b1000111010 )
b1000111011 *
#2900
0$
#2910
b1010 #
1$
b1000100100 '
b1000100101 (
b1000111100 )
b1000111101 *
#2920
0$
#2930
b1011 #
1$
b1000100110 '
b1000100111 (
b1000111110 )
b1000111111 *
1+
