hardware/mem_counter_test/conv2_k_mem_read.sv
//Module used to provide access to 6 kernels with two counters at once
// counter/addresser for Convolution 2 layer weight memory read
module conv2_k_mem_read (input logic clk, reset, enable,
                        output logic [7:0] addr0, addr1,
                        output logic done);

    always_ff @(posedge clk or posedge reset) begin
        if (reset == 1'b1) begin
            addr0 <= 8'b00000000;
            addr1 <= 8'b01001011;
        end
        else if (enable == 1'b1 && done == 1'b0) begin
            addr0 <= addr0 + 8'b00000001;
            addr1 <= addr1 + 8'b00000001;
        end
    end
    
    always_comb begin
        //Count until addr1 reaches end of 6th kernel, i.e. 6 * 25 - 1 = 149
        if(addr1 == 8'b10010101) begin
            done = 1'b1;
        end
    end

endmodule

hardware/mem_counter_test/conv2_k_mem_read.vcd
$version Generated by VerilatedVcd $end
$date Thu May  5 10:31:04 2022
 $end
$timescale   1ns $end

 $scope module TOP $end
  $var wire  8 & addr0 [7:0] $end
  $var wire  8 ' addr1 [7:0] $end
  $var wire  1 # clk $end
  $var wire  1 ( done $end
  $var wire  1 % enable $end
  $var wire  1 $ reset $end
  $scope module conv2_k_mem_read $end
   $var wire  8 & addr0 [7:0] $end
   $var wire  8 ' addr1 [7:0] $end
   $var wire  1 # clk $end
   $var wire  1 ( done $end
   $var wire  1 % enable $end
   $var wire  1 $ reset $end
  $upscope $end
 $upscope $end
$enddefinitions $end


#0
0#
0$
0%
b00000000 &
b00000000 '
0(
#10
1#
#20
0#
1$
b01001011 '
#30
1#
#40
0#
#50
1#
#60
0#
0$
#70
1#
#80
0#
1%
#90
1#
b00000001 &
b01001100 '
#90
#100
0#
#110
1#
b00000010 &
b01001101 '
#120
0#
#130
1#
b00000011 &
b01001110 '
#140
0#
#150
1#
b00000100 &
b01001111 '
#160
0#
#170
1#
b00000101 &
b01010000 '
#180
0#
#190
1#
b00000110 &
b01010001 '
#200
0#
#210
1#
b00000111 &
b01010010 '
#220
0#
#230
1#
b00001000 &
b01010011 '
#240
0#
#250
1#
b00001001 &
b01010100 '
#260
0#
#270
1#
b00001010 &
b01010101 '
#280
0#
#290
1#
b00001011 &
b01010110 '
#300
0#
#310
1#
b00001100 &
b01010111 '
#320
0#
#330
1#
b00001101 &
b01011000 '
#340
0#
#350
1#
b00001110 &
b01011001 '
#360
0#
#370
1#
b00001111 &
b01011010 '
#380
0#
#390
1#
b00010000 &
b01011011 '
#400
0#
#410
1#
b00010001 &
b01011100 '
#420
0#
#430
1#
b00010010 &
b01011101 '
#440
0#
#450
1#
b00010011 &
b01011110 '
#460
0#
#470
1#
b00010100 &
b01011111 '
#480
0#
#490
1#
b00010101 &
b01100000 '
#500
0#
#510
1#
b00010110 &
b01100001 '
#520
0#
#530
1#
b00010111 &
b01100010 '
#540
0#
#550
1#
b00011000 &
b01100011 '
#560
0#
#570
1#
b00011001 &
b01100100 '
#580
0#
#590
1#
b00011010 &
b01100101 '
#600
0#
#610
1#
b00011011 &
b01100110 '
#620
0#
#630
1#
b00011100 &
b01100111 '
#640
0#
#650
1#
b00011101 &
b01101000 '
#660
0#
#670
1#
b00011110 &
b01101001 '
#680
0#
#690
1#
b00011111 &
b01101010 '
#700
0#
#710
1#
b00100000 &
b01101011 '
#720
0#
#730
1#
b00100001 &
b01101100 '
#740
0#
#750
1#
b00100010 &
b01101101 '
#760
0#
#770
1#
b00100011 &
b01101110 '
#780
0#
#790
1#
b00100100 &
b01101111 '
#800
0#
#810
1#
b00100101 &
b01110000 '
#820
0#
#830
1#
b00100110 &
b01110001 '
#840
0#
#850
1#
b00100111 &
b01110010 '
#860
0#
#870
1#
b00101000 &
b01110011 '
#880
0#
#890
1#
b00101001 &
b01110100 '
#900
0#
#910
1#
b00101010 &
b01110101 '
#920
0#
#930
1#
b00101011 &
b01110110 '
#940
0#
#950
1#
b00101100 &
b01110111 '
#960
0#
#970
1#
b00101101 &
b01111000 '
#980
0#
#990
1#
b00101110 &
b01111001 '
#1000
0#
#1010
1#
b00101111 &
b01111010 '
#1020
0#
#1030
1#
b00110000 &
b01111011 '
#1040
0#
#1050
1#
b00110001 &
b01111100 '
#1060
0#
#1070
1#
b00110010 &
b01111101 '
#1080
0#
#1090
1#
b00110011 &
b01111110 '
#1100
0#
#1110
1#
b00110100 &
b01111111 '
#1120
0#
#1130
1#
b00110101 &
b10000000 '
#1140
0#
#1150
1#
b00110110 &
b10000001 '
#1160
0#
#1170
1#
b00110111 &
b10000010 '
#1180
0#
#1190
1#
b00111000 &
b10000011 '
#1200
0#
#1210
1#
b00111001 &
b10000100 '
#1220
0#
#1230
1#
b00111010 &
b10000101 '
#1240
0#
#1250
1#
b00111011 &
b10000110 '
#1260
0#
#1270
1#
b00111100 &
b10000111 '
#1280
0#
#1290
1#
b00111101 &
b10001000 '
#1300
0#
#1310
1#
b00111110 &
b10001001 '
#1320
0#
#1330
1#
b00111111 &
b10001010 '
#1340
0#
#1350
1#
b01000000 &
b10001011 '
#1360
0#
#1370
1#
b01000001 &
b10001100 '
#1380
0#
#1390
1#
b01000010 &
b10001101 '
#1400
0#
#1410
1#
b01000011 &
b10001110 '
#1420
0#
#1430
1#
b01000100 &
b10001111 '
#1440
0#
#1450
1#
b01000101 &
b10010000 '
#1460
0#
#1470
1#
b01000110 &
b10010001 '
#1480
0#
#1490
1#
b01000111 &
b10010010 '
#1500
0#
#1510
1#
b01001000 &
b10010011 '
#1520
0#
#1530
1#
b01001001 &
b10010100 '
#1540
0#
#1550
1#
b01001010 &
b10010101 '
1(
