hardware/mem_counter_test/img_mem_read.sv
//img_mem_read is responsible for one conv1 output image and uses four output addresses in parallel. Each processes a quarter of the image, the offset between addresses is 28 * 24 / 4 = 168
// counter/addresser for input image memory read
module img_mem_read (input logic clk, reset, enable,
                     output logic [9:0] addr0, addr1, addr2, addr3, 
                     output logic done);

    //kernel row and column count
    logic [2:0] rowcount, columncount;
    //counter for position within image row
    logic [4:0] i_count;

    always_ff @(posedge clk or posedge reset) begin
        if (reset == 1'b1) begin
            addr0 <= 10'b0000000000;
            addr1 <= 10'b0010101000;
            addr2 <= 10'b0101010000;
            addr3 <= 10'b0111111000;
            i_count <= 5'b00000;
        end
        else if (enable == 1'b1 && done == 1'b0) begin
            if (i_count == 5'b10111 && rowcount == 3'b100 && columncount == 3'b100) begin
                //done with applying the kernel over an entire image row, go to the next row
                //Move addresses 4 rows up, 27 pixels back and 1 row down, i.e. -111
                i_count <= 5'b00000;
                columncount <= 3'b000;
                rowcount <= 3'b000;
                addr0 <= addr0 - 10'b0001101111;
                addr1 <= addr1 - 10'b0001101111;
                addr2 <= addr2 - 10'b0001101111;
                addr3 <= addr3 - 10'b0001101111;
            end
            else if (rowcount == 3'b100 && columncount == 3'b100) begin
                //done with a position for the kernel, move forward to the next position. Move 4 rows up, 4 pixels back and 1 pixel forward, i.e. -115
                columncount <= 3'b000;
                rowcount <= 3'b000;
                addr0 <= addr0 - 10'b0001110011;
                addr1 <= addr1 - 10'b0001110011;
                addr2 <= addr2 - 10'b0001110011;
                addr3 <= addr3 - 10'b0001110011;
                i_count <= i_count + 5'b00001;
            end
            else if (columncount == 3'b100) begin
                //kernel row has been processed, move addresses one row down and 4 pixels back, i.e. + 24
                columncount <= 3'b000;
                rowcount <= rowcount + 3'b001;
                addr0 <= addr0 + 10'b0000011000;
                addr1 <= addr1 + 10'b0000011000;
                addr2 <= addr2 + 10'b0000011000;
                addr3 <= addr3 + 10'b0000011000;
            end
            else begin
                addr0 <= addr0 + 10'b0000000001;
                addr1 <= addr1 + 10'b0000000001;
                addr2 <= addr2 + 10'b0000000001;
                addr3 <= addr3 + 10'b0000000001;
                columncount <= columncount + 3'b001;
            end
        end
    end

    always_comb begin
        if(addr3 == 10'b1100001111) begin
            done = 1'b1;
        end
    end

endmodule

hardware/mem_counter_test/img_mem_read.vcd
$version Generated by VerilatedVcd $end
$date Thu May  5 10:34:17 2022
 $end
$timescale   1ns $end

 $scope module TOP $end
  $var wire 10 ) addr0 [9:0] $end
  $var wire 10 * addr1 [9:0] $end
  $var wire 10 + addr2 [9:0] $end
  $var wire 10 , addr3 [9:0] $end
  $var wire  1 & clk $end
  $var wire  1 - done $end
  $var wire  1 ( enable $end
  $var wire  1 ' reset $end
  $scope module img_mem_read $end
   $var wire 10 ) addr0 [9:0] $end
   $var wire 10 * addr1 [9:0] $end
   $var wire 10 + addr2 [9:0] $end
   $var wire 10 , addr3 [9:0] $end
   $var wire  1 & clk $end
   $var wire  3 $ columncount [2:0] $end
   $var wire  1 - done $end
   $var wire  1 ( enable $end
   $var wire  5 % i_count [4:0] $end
   $var wire  1 ' reset $end
   $var wire  3 # rowcount [2:0] $end
  $upscope $end
 $upscope $end
$enddefinitions $end


#0
b000 #
b000 $
b00000 %
0&
0'
0(
b0000000000 )
b0000000000 *
b0000000000 +
b0000000000 ,
0-
#10
1&
#20
0&
1'
b0010101000 *
b0101010000 +
b0111111000 ,
#30
1&
#40
0&
#50
1&
#60
0&
0'
#70
1&
#80
0&
1(
#90
b001 $
1&
b0000000001 )
b0010101001 *
b0101010001 +
b0111111001 ,
#100
0&
#110
b010 $
1&
b0000000010 )
b0010101010 *
b0101010010 +
b0111111010 ,
#120
0&
#130
b011 $
1&
b0000000011 )
b0010101011 *
b0101010011 +
b0111111011 ,
#140
0&
#150
b100 $
1&
b0000000100 )
b0010101100 *
b0101010100 +
b0111111100 ,
#160
0&
#170
b001 #
b000 $
1&
b0000011100 )
b0011000100 *
b0101101100 +
b1000010100 ,
#180
0&
#190
b001 $
1&
b0000011101 )
b0011000101 *
b0101101101 +
b1000010101 ,
#200
0&
#210
b010 $
1&
b0000011110 )
b0011000110 *
b0101101110 +
b1000010110 ,
#220
0&
#230
b011 $
1&
b0000011111 )
b0011000111 *
b0101101111 +
b1000010111 ,
#240
0&
#250
b100 $
1&
b0000100000 )
b0011001000 *
b0101110000 +
b1000011000 ,
#260
0&
#270
b010 #
b000 $
1&
b0000111000 )
b0011100000 *
b0110001000 +
b1000110000 ,
#280
0&
#290
b001 $
1&
b0000111001 )
b0011100001 *
b0110001001 +
b1000110001 ,
#300
0&
#310
b010 $
1&
b0000111010 )
b0011100010 *
b0110001010 +
b1000110010 ,
#320
0&
#330
b011 $
1&
b0000111011 )
b0011100011 *
b0110001011 +
b1000110011 ,
#340
0&
#350
b100 $
1&
b0000111100 )
b0011100100 *
b0110001100 +
b1000110100 ,
#360
0&
#370
b011 #
b000 $
1&
b0001010100 )
b0011111100 *
b0110100100 +
b1001001100 ,
#380
0&
#390
b001 $
1&
b0001010101 )
b0011111101 *
b0110100101 +
b1001001101 ,
#400
0&
#410
b010 $
1&
b0001010110 )
b0011111110 *
b0110100110 +
b1001001110 ,
#420
0&
#430
b011 $
1&
b0001010111 )
b0011111111 *
b0110100111 +
b1001001111 ,
#440
0&
#450
b100 $
1&
b0001011000 )
b0100000000 *
b0110101000 +
b1001010000 ,
#460
0&
#470
b100 #
b000 $
1&
b0001110000 )
b0100011000 *
b0111000000 +
b1001101000 ,
#480
0&
#490
b001 $
1&
b0001110001 )
b0100011001 *
b0111000001 +
b1001101001 ,
#500
0&
#510
b010 $
1&
b0001110010 )
b0100011010 *
b0111000010 +
b1001101010 ,
#520
0&
#530
b011 $
1&
b0001110011 )
b0100011011 *
b0111000011 +
b1001101011 ,
#540
0&
#550
b100 $
1&
b0001110100 )
b0100011100 *
b0111000100 +
b1001101100 ,
#560
0&
#570
b000 #
b000 $
b00001 %
1&
b0000000001 )
b0010101001 *
b0101010001 +
b0111111001 ,
#580
0&
#590
b001 $
1&
b0000000010 )
b0010101010 *
b0101010010 +
b0111111010 ,
#600
0&
#610
b010 $
1&
b0000000011 )
b0010101011 *
b0101010011 +
b0111111011 ,
#620
0&
#630
b011 $
1&
b0000000100 )
b0010101100 *
b0101010100 +
b0111111100 ,
#640
0&
#650
b100 $
1&
b0000000101 )
b0010101101 *
b0101010101 +
b0111111101 ,
#660
0&
#670
b001 #
b000 $
1&
b0000011101 )
b0011000101 *
b0101101101 +
b1000010101 ,
#680
0&
#690
b001 $
1&
b0000011110 )
b0011000110 *
b0101101110 +
b1000010110 ,
#700
0&
#710
b010 $
1&
b0000011111 )
b0011000111 *
b0101101111 +
b1000010111 ,
#720
0&
#730
b011 $
1&
b0000100000 )
b0011001000 *
b0101110000 +
b1000011000 ,
#740
0&
#750
b100 $
1&
b0000100001 )
b0011001001 *
b0101110001 +
b1000011001 ,
#760
0&
#770
b010 #
b000 $
1&
b0000111001 )
b0011100001 *
b0110001001 +
b1000110001 ,
#780
0&
#790
b001 $
1&
b0000111010 )
b0011100010 *
b0110001010 +
b1000110010 ,
#800
0&
#810
b010 $
1&
b0000111011 )
b0011100011 *
b0110001011 +
b1000110011 ,
#820
0&
#830
b011 $
1&
b0000111100 )
b0011100100 *
b0110001100 +
b1000110100 ,
#840
0&
#850
b100 $
1&
b0000111101 )
b0011100101 *
b0110001101 +
b1000110101 ,
#860
0&
#870
b011 #
b000 $
1&
b0001010101 )
b0011111101 *
b0110100101 +
b1001001101 ,
#880
0&
#890
b001 $
1&
b0001010110 )
b0011111110 *
b0110100110 +
b1001001110 ,
#900
0&
#910
b010 $
1&
b0001010111 )
b0011111111 *
b0110100111 +
b1001001111 ,
#920
0&
#930
b011 $
1&
b0001011000 )
b0100000000 *
b0110101000 +
b1001010000 ,
#940
0&
#950
b100 $
1&
b0001011001 )
b0100000001 *
b0110101001 +
b1001010001 ,
#960
0&
#970
b100 #
b000 $
1&
b0001110001 )
b0100011001 *
b0111000001 +
b1001101001 ,
#980
0&
#990
b001 $
1&
b0001110010 )
b0100011010 *
b0111000010 +
b1001101010 ,
#1000
0&
#1010
b010 $
1&
b0001110011 )
b0100011011 *
b0111000011 +
b1001101011 ,
#1020
0&
#1030
b011 $
1&
b0001110100 )
b0100011100 *
b0111000100 +
b1001101100 ,
#1040
0&
#1050
b100 $
1&
b0001110101 )
b0100011101 *
b0111000101 +
b1001101101 ,
#1060
0&
#1070
b000 #
b000 $
b00010 %
1&
b0000000010 )
b0010101010 *
b0101010010 +
b0111111010 ,
#1080
0&
#1090
b001 $
1&
b0000000011 )
b0010101011 *
b0101010011 +
b0111111011 ,
#1100
0&
#1110
b010 $
1&
b0000000100 )
b0010101100 *
b0101010100 +
b0111111100 ,
#1120
0&
#1130
b011 $
1&
b0000000101 )
b0010101101 *
b0101010101 +
b0111111101 ,
#1140
0&
#1150
b100 $
1&
b0000000110 )
b0010101110 *
b0101010110 +
b0111111110 ,
#1160
0&
#1170
b001 #
b000 $
1&
b0000011110 )
b0011000110 *
b0101101110 +
b1000010110 ,
#1180
0&
#1190
b001 $
1&
b0000011111 )
b0011000111 *
b0101101111 +
b1000010111 ,
#1200
0&
#1210
b010 $
1&
b0000100000 )
b0011001000 *
b0101110000 +
b1000011000 ,
#1220
0&
#1230
b011 $
1&
b0000100001 )
b0011001001 *
b0101110001 +
b1000011001 ,
#1240
0&
#1250
b100 $
1&
b0000100010 )
b0011001010 *
b0101110010 +
b1000011010 ,
#1260
0&
#1270
b010 #
b000 $
1&
b0000111010 )
b0011100010 *
b0110001010 +
b1000110010 ,
#1280
0&
#1290
b001 $
1&
b0000111011 )
b0011100011 *
b0110001011 +
b1000110011 ,
#1300
0&
#1310
b010 $
1&
b0000111100 )
b0011100100 *
b0110001100 +
b1000110100 ,
#1320
0&
#1330
b011 $
1&
b0000111101 )
b0011100101 *
b0110001101 +
b1000110101 ,
#1340
0&
#1350
b100 $
1&
b0000111110 )
b0011100110 *
b0110001110 +
b1000110110 ,
#1360
0&
#1370
b011 #
b000 $
1&
b0001010110 )
b0011111110 *
b0110100110 +
b1001001110 ,
#1380
0&
#1390
b001 $
1&
b0001010111 )
b0011111111 *
b0110100111 +
b1001001111 ,
#1400
0&
#1410
b010 $
1&
b0001011000 )
b0100000000 *
b0110101000 +
b1001010000 ,
#1420
0&
#1430
b011 $
1&
b0001011001 )
b0100000001 *
b0110101001 +
b1001010001 ,
#1440
0&
#1450
b100 $
1&
b0001011010 )
b0100000010 *
b0110101010 +
b1001010010 ,
#1460
0&
#1470
b100 #
b000 $
1&
b0001110010 )
b0100011010 *
b0111000010 +
b1001101010 ,
#1480
0&
#1490
b001 $
1&
b0001110011 )
b0100011011 *
b0111000011 +
b1001101011 ,
#1500
0&
#1510
b010 $
1&
b0001110100 )
b0100011100 *
b0111000100 +
b1001101100 ,
#1520
0&
#1530
b011 $
1&
b0001110101 )
b0100011101 *
b0111000101 +
b1001101101 ,
#1540
0&
#1550
b100 $
1&
b0001110110 )
b0100011110 *
b0111000110 +
b1001101110 ,
#1560
0&
#1570
b000 #
b000 $
b00011 %
1&
b0000000011 )
b0010101011 *
b0101010011 +
b0111111011 ,
#1580
0&
#1590
b001 $
1&
b0000000100 )
b0010101100 *
b0101010100 +
b0111111100 ,
#1600
0&
#1610
b010 $
1&
b0000000101 )
b0010101101 *
b0101010101 +
b0111111101 ,
#1620
0&
#1630
b011 $
1&
b0000000110 )
b0010101110 *
b0101010110 +
b0111111110 ,
#1640
0&
#1650
b100 $
1&
b0000000111 )
b0010101111 *
b0101010111 +
b0111111111 ,
#1660
0&
#1670
b001 #
b000 $
1&
b0000011111 )
b0011000111 *
b0101101111 +
b1000010111 ,
#1680
0&
#1690
b001 $
1&
b0000100000 )
b0011001000 *
b0101110000 +
b1000011000 ,
#1700
0&
#1710
b010 $
1&
b0000100001 )
b0011001001 *
b0101110001 +
b1000011001 ,
#1720
0&
#1730
b011 $
1&
b0000100010 )
b0011001010 *
b0101110010 +
b1000011010 ,
#1740
0&
#1750
b100 $
1&
b0000100011 )
b0011001011 *
b0101110011 +
b1000011011 ,
#1760
0&
#1770
b010 #
b000 $
1&
b0000111011 )
b0011100011 *
b0110001011 +
b1000110011 ,
#1780
0&
#1790
b001 $
1&
b0000111100 )
b0011100100 *
b0110001100 +
b1000110100 ,
#1800
0&
#1810
b010 $
1&
b0000111101 )
b0011100101 *
b0110001101 +
b1000110101 ,
#1820
0&
#1830
b011 $
1&
b0000111110 )
b0011100110 *
b0110001110 +
b1000110110 ,
#1840
0&
#1850
b100 $
1&
b0000111111 )
b0011100111 *
b0110001111 +
b1000110111 ,
#1860
0&
#1870
b011 #
b000 $
1&
b0001010111 )
b0011111111 *
b0110100111 +
b1001001111 ,
#1880
0&
#1890
b001 $
1&
b0001011000 )
b0100000000 *
b0110101000 +
b1001010000 ,
#1900
0&
#1910
b010 $
1&
b0001011001 )
b0100000001 *
b0110101001 +
b1001010001 ,
#1920
0&
#1930
b011 $
1&
b0001011010 )
b0100000010 *
b0110101010 +
b1001010010 ,
#1940
0&
#1950
b100 $
1&
b0001011011 )
b0100000011 *
b0110101011 +
b1001010011 ,
#1960
0&
#1970
b100 #
b000 $
1&
b0001110011 )
b0100011011 *
b0111000011 +
b1001101011 ,
#1980
0&
#1990
b001 $
1&
b0001110100 )
b0100011100 *
b0111000100 +
b1001101100 ,
#2000
0&
#2010
b010 $
1&
b0001110101 )
b0100011101 *
b0111000101 +
b1001101101 ,
#2020
0&
#2030
b011 $
1&
b0001110110 )
b0100011110 *
b0111000110 +
b1001101110 ,
#2040
0&
#2050
b100 $
1&
b0001110111 )
b0100011111 *
b0111000111 +
b1001101111 ,
#2060
0&
#2070
b000 #
b000 $
b00100 %
1&
b0000000100 )
b0010101100 *
b0101010100 +
b0111111100 ,
#2080
0&
#2090
b001 $
1&
b0000000101 )
b0010101101 *
b0101010101 +
b0111111101 ,
#2100
0&
#2110
b010 $
1&
b0000000110 )
b0010101110 *
b0101010110 +
b0111111110 ,
#2120
0&
#2130
b011 $
1&
b0000000111 )
b0010101111 *
b0101010111 +
b0111111111 ,
#2140
0&
#2150
b100 $
1&
b0000001000 )
b0010110000 *
b0101011000 +
b1000000000 ,
#2160
0&
#2170
b001 #
b000 $
1&
b0000100000 )
b0011001000 *
b0101110000 +
b1000011000 ,
#2180
0&
#2190
b001 $
1&
b0000100001 )
b0011001001 *
b0101110001 +
b1000011001 ,
#2200
0&
#2210
b010 $
1&
b0000100010 )
b0011001010 *
b0101110010 +
b1000011010 ,
#2220
0&
#2230
b011 $
1&
b0000100011 )
b0011001011 *
b0101110011 +
b1000011011 ,
#2240
0&
#2250
b100 $
1&
b0000100100 )
b0011001100 *
b0101110100 +
b1000011100 ,
#2260
0&
#2270
b010 #
b000 $
1&
b0000111100 )
b0011100100 *
b0110001100 +
b1000110100 ,
#2280
0&
#2290
b001 $
1&
b0000111101 )
b0011100101 *
b0110001101 +
b1000110101 ,
#2300
0&
#2310
b010 $
1&
b0000111110 )
b0011100110 *
b0110001110 +
b1000110110 ,
#2320
0&
#2330
b011 $
1&
b0000111111 )
b0011100111 *
b0110001111 +
b1000110111 ,
#2340
0&
#2350
b100 $
1&
b0001000000 )
b0011101000 *
b0110010000 +
b1000111000 ,
#2360
0&
#2370
b011 #
b000 $
1&
b0001011000 )
b0100000000 *
b0110101000 +
b1001010000 ,
#2380
0&
#2390
b001 $
1&
b0001011001 )
b0100000001 *
b0110101001 +
b1001010001 ,
#2400
0&
#2410
b010 $
1&
b0001011010 )
b0100000010 *
b0110101010 +
b1001010010 ,
#2420
0&
#2430
b011 $
1&
b0001011011 )
b0100000011 *
b0110101011 +
b1001010011 ,
#2440
0&
#2450
b100 $
1&
b0001011100 )
b0100000100 *
b0110101100 +
b1001010100 ,
#2460
0&
#2470
b100 #
b000 $
1&
b0001110100 )
b0100011100 *
b0111000100 +
b1001101100 ,
#2480
0&
#2490
b001 $
1&
b0001110101 )
b0100011101 *
b0111000101 +
b1001101101 ,
#2500
0&
#2510
b010 $
1&
b0001110110 )
b0100011110 *
b0111000110 +
b1001101110 ,
#2520
0&
#2530
b011 $
1&
b0001110111 )
b0100011111 *
b0111000111 +
b1001101111 ,
#2540
0&
#2550
b100 $
1&
b0001111000 )
b0100100000 *
b0111001000 +
b1001110000 ,
#2560
0&
#2570
b000 #
b000 $
b00101 %
1&
b0000000101 )
b0010101101 *
b0101010101 +
b0111111101 ,
#2580
0&
#2590
b001 $
1&
b0000000110 )
b0010101110 *
b0101010110 +
b0111111110 ,
#2600
0&
#2610
b010 $
1&
b0000000111 )
b0010101111 *
b0101010111 +
b0111111111 ,
#2620
0&
#2630
b011 $
1&
b0000001000 )
b0010110000 *
b0101011000 +
b1000000000 ,
#2640
0&
#2650
b100 $
1&
b0000001001 )
b0010110001 *
b0101011001 +
b1000000001 ,
#2660
0&
#2670
b001 #
b000 $
1&
b0000100001 )
b0011001001 *
b0101110001 +
b1000011001 ,
#2680
0&
#2690
b001 $
1&
b0000100010 )
b0011001010 *
b0101110010 +
b1000011010 ,
#2700
0&
#2710
b010 $
1&
b0000100011 )
b0011001011 *
b0101110011 +
b1000011011 ,
#2720
0&
#2730
b011 $
1&
b0000100100 )
b0011001100 *
b0101110100 +
b1000011100 ,
#2740
0&
#2750
b100 $
1&
b0000100101 )
b0011001101 *
b0101110101 +
b1000011101 ,
#2760
0&
#2770
b010 #
b000 $
1&
b0000111101 )
b0011100101 *
b0110001101 +
b1000110101 ,
#2780
0&
#2790
b001 $
1&
b0000111110 )
b0011100110 *
b0110001110 +
b1000110110 ,
#2800
0&
#2810
b010 $
1&
b0000111111 )
b0011100111 *
b0110001111 +
b1000110111 ,
#2820
0&
#2830
b011 $
1&
b0001000000 )
b0011101000 *
b0110010000 +
b1000111000 ,
#2840
0&
#2850
b100 $
1&
b0001000001 )
b0011101001 *
b0110010001 +
b1000111001 ,
#2860
0&
#2870
b011 #
b000 $
1&
b0001011001 )
b0100000001 *
b0110101001 +
b1001010001 ,
#2880
0&
#2890
b001 $
1&
b0001011010 )
b0100000010 *
b0110101010 +
b1001010010 ,
#2900
0&
#2910
b010 $
1&
b0001011011 )
b0100000011 *
b0110101011 +
b1001010011 ,
#2920
0&
#2930
b011 $
1&
b0001011100 )
b0100000100 *
b0110101100 +
b1001010100 ,
#2940
0&
#2950
b100 $
1&
b0001011101 )
b0100000101 *
b0110101101 +
b1001010101 ,
#2960
0&
#2970
b100 #
b000 $
1&
b0001110101 )
b0100011101 *
b0111000101 +
b1001101101 ,
#2980
0&
#2990
b001 $
1&
b0001110110 )
b0100011110 *
b0111000110 +
b1001101110 ,
#3000
0&
#3010
b010 $
1&
b0001110111 )
b0100011111 *
b0111000111 +
b1001101111 ,
#3020
0&
#3030
b011 $
1&
b0001111000 )
b0100100000 *
b0111001000 +
b1001110000 ,
#3040
0&
#3050
b100 $
1&
b0001111001 )
b0100100001 *
b0111001001 +
b1001110001 ,
#3060
0&
#3070
b000 #
b000 $
b00110 %
1&
b0000000110 )
b0010101110 *
b0101010110 +
b0111111110 ,
#3080
0&
#3090
b001 $
1&
b0000000111 )
b0010101111 *
b0101010111 +
b0111111111 ,
#3100
0&
#3110
b010 $
1&
b0000001000 )
b0010110000 *
b0101011000 +
b1000000000 ,
#3120
0&
#3130
b011 $
1&
b0000001001 )
b0010110001 *
b0101011001 +
b1000000001 ,
#3140
0&
#3150
b100 $
1&
b0000001010 )
b0010110010 *
b0101011010 +
b1000000010 ,
#3160
0&
#3170
b001 #
b000 $
1&
b0000100010 )
b0011001010 *
b0101110010 +
b1000011010 ,
#3180
0&
#3190
b001 $
1&
b0000100011 )
b0011001011 *
b0101110011 +
b1000011011 ,
#3200
0&
#3210
b010 $
1&
b0000100100 )
b0011001100 *
b0101110100 +
b1000011100 ,
#3220
0&
#3230
b011 $
1&
b0000100101 )
b0011001101 *
b0101110101 +
b1000011101 ,
#3240
0&
#3250
b100 $
1&
b0000100110 )
b0011001110 *
b0101110110 +
b1000011110 ,
#3260
0&
#3270
b010 #
b000 $
1&
b0000111110 )
b0011100110 *
b0110001110 +
b1000110110 ,
#3280
0&
#3290
b001 $
1&
b0000111111 )
b0011100111 *
b0110001111 +
b1000110111 ,
#3300
0&
#3310
b010 $
1&
b0001000000 )
b0011101000 *
b0110010000 +
b1000111000 ,
#3320
0&
#3330
b011 $
1&
b0001000001 )
b0011101001 *
b0110010001 +
b1000111001 ,
#3340
0&
#3350
b100 $
1&
b0001000010 )
b0011101010 *
b0110010010 +
b1000111010 ,
#3360
0&
#3370
b011 #
b000 $
1&
b0001011010 )
b0100000010 *
b0110101010 +
b1001010010 ,
#3380
0&
#3390
b001 $
1&
b0001011011 )
b0100000011 *
b0110101011 +
b1001010011 ,
#3400
0&
#3410
b010 $
1&
b0001011100 )
b0100000100 *
b0110101100 +
b1001010100 ,
#3420
0&
#3430
b011 $
1&
b0001011101 )
b0100000101 *
b0110101101 +
b1001010101 ,
#3440
0&
#3450
b100 $
1&
b0001011110 )
b0100000110 *
b0110101110 +
b1001010110 ,
#3460
0&
#3470
b100 #
b000 $
1&
b0001110110 )
b0100011110 *
b0111000110 +
b1001101110 ,
#3480
0&
#3490
b001 $
1&
b0001110111 )
b0100011111 *
b0111000111 +
b1001101111 ,
#3500
0&
#3510
b010 $
1&
b0001111000 )
b0100100000 *
b0111001000 +
b1001110000 ,
#3520
0&
#3530
b011 $
1&
b0001111001 )
b0100100001 *
b0111001001 +
b1001110001 ,
#3540
0&
#3550
b100 $
1&
b0001111010 )
b0100100010 *
b0111001010 +
b1001110010 ,
#3560
0&
#3570
b000 #
b000 $
b00111 %
1&
b0000000111 )
b0010101111 *
b0101010111 +
b0111111111 ,
#3580
0&
#3590
b001 $
1&
b0000001000 )
b0010110000 *
b0101011000 +
b1000000000 ,
#3600
0&
#3610
b010 $
1&
b0000001001 )
b0010110001 *
b0101011001 +
b1000000001 ,
#3620
0&
#3630
b011 $
1&
b0000001010 )
b0010110010 *
b0101011010 +
b1000000010 ,
#3640
0&
#3650
b100 $
1&
b0000001011 )
b0010110011 *
b0101011011 +
b1000000011 ,
#3660
0&
#3670
b001 #
b000 $
1&
b0000100011 )
b0011001011 *
b0101110011 +
b1000011011 ,
#3680
0&
#3690
b001 $
1&
b0000100100 )
b0011001100 *
b0101110100 +
b1000011100 ,
#3700
0&
#3710
b010 $
1&
b0000100101 )
b0011001101 *
b0101110101 +
b1000011101 ,
#3720
0&
#3730
b011 $
1&
b0000100110 )
b0011001110 *
b0101110110 +
b1000011110 ,
#3740
0&
#3750
b100 $
1&
b0000100111 )
b0011001111 *
b0101110111 +
b1000011111 ,
#3760
0&
#3770
b010 #
b000 $
1&
b0000111111 )
b0011100111 *
b0110001111 +
b1000110111 ,
#3780
0&
#3790
b001 $
1&
b0001000000 )
b0011101000 *
b0110010000 +
b1000111000 ,
#3800
0&
#3810
b010 $
1&
b0001000001 )
b0011101001 *
b0110010001 +
b1000111001 ,
#3820
0&
#3830
b011 $
1&
b0001000010 )
b0011101010 *
b0110010010 +
b1000111010 ,
#3840
0&
#3850
b100 $
1&
b0001000011 )
b0011101011 *
b0110010011 +
b1000111011 ,
#3860
0&
#3870
b011 #
b000 $
1&
b0001011011 )
b0100000011 *
b0110101011 +
b1001010011 ,
#3880
0&
#3890
b001 $
1&
b0001011100 )
b0100000100 *
b0110101100 +
b1001010100 ,
#3900
0&
#3910
b010 $
1&
b0001011101 )
b0100000101 *
b0110101101 +
b1001010101 ,
#3920
0&
#3930
b011 $
1&
b0001011110 )
b0100000110 *
b0110101110 +
b1001010110 ,
#3940
0&
#3950
b100 $
1&
b0001011111 )
b0100000111 *
b0110101111 +
b1001010111 ,
#3960
0&
#3970
b100 #
b000 $
1&
b0001110111 )
b0100011111 *
b0111000111 +
b1001101111 ,
#3980
0&
#3990
b001 $
1&
b0001111000 )
b0100100000 *
b0111001000 +
b1001110000 ,
#4000
0&
#4010
b010 $
1&
b0001111001 )
b0100100001 *
b0111001001 +
b1001110001 ,
#4020
0&
#4030
b011 $
1&
b0001111010 )
b0100100010 *
b0111001010 +
b1001110010 ,
#4040
0&
#4050
b100 $
1&
b0001111011 )
b0100100011 *
b0111001011 +
b1001110011 ,
#4060
0&
#4070
b000 #
b000 $
b01000 %
1&
b0000001000 )
b0010110000 *
b0101011000 +
b1000000000 ,
#4080
0&
#4090
b001 $
1&
b0000001001 )
b0010110001 *
b0101011001 +
b1000000001 ,
#4100
0&
#4110
b010 $
1&
b0000001010 )
b0010110010 *
b0101011010 +
b1000000010 ,
#4120
0&
#4130
b011 $
1&
b0000001011 )
b0010110011 *
b0101011011 +
b1000000011 ,
#4140
0&
#4150
b100 $
1&
b0000001100 )
b0010110100 *
b0101011100 +
b1000000100 ,
#4160
0&
#4170
b001 #
b000 $
1&
b0000100100 )
b0011001100 *
b0101110100 +
b1000011100 ,
#4180
0&
#4190
b001 $
1&
b0000100101 )
b0011001101 *
b0101110101 +
b1000011101 ,
#4200
0&
#4210
b010 $
1&
b0000100110 )
b0011001110 *
b0101110110 +
b1000011110 ,
#4220
0&
#4230
b011 $
1&
b0000100111 )
b0011001111 *
b0101110111 +
b1000011111 ,
#4240
0&
#4250
b100 $
1&
b0000101000 )
b0011010000 *
b0101111000 +
b1000100000 ,
#4260
0&
#4270
b010 #
b000 $
1&
b0001000000 )
b0011101000 *
b0110010000 +
b1000111000 ,
#4280
0&
#4290
b001 $
1&
b0001000001 )
b0011101001 *
b0110010001 +
b1000111001 ,
#4300
0&
#4310
b010 $
1&
b0001000010 )
b0011101010 *
b0110010010 +
b1000111010 ,
#4320
0&
#4330
b011 $
1&
b0001000011 )
b0011101011 *
b0110010011 +
b1000111011 ,
#4340
0&
#4350
b100 $
1&
b0001000100 )
b0011101100 *
b0110010100 +
b1000111100 ,
#4360
0&
#4370
b011 #
b000 $
1&
b0001011100 )
b0100000100 *
b0110101100 +
b1001010100 ,
#4380
0&
#4390
b001 $
1&
b0001011101 )
b0100000101 *
b0110101101 +
b1001010101 ,
#4400
0&
#4410
b010 $
1&
b0001011110 )
b0100000110 *
b0110101110 +
b1001010110 ,
#4420
0&
#4430
b011 $
1&
b0001011111 )
b0100000111 *
b0110101111 +
b1001010111 ,
#4440
0&
#4450
b100 $
1&
b0001100000 )
b0100001000 *
b0110110000 +
b1001011000 ,
#4460
0&
#4470
b100 #
b000 $
1&
b0001111000 )
b0100100000 *
b0111001000 +
b1001110000 ,
#4480
0&
#4490
b001 $
1&
b0001111001 )
b0100100001 *
b0111001001 +
b1001110001 ,
#4500
0&
#4510
b010 $
1&
b0001111010 )
b0100100010 *
b0111001010 +
b1001110010 ,
#4520
0&
#4530
b011 $
1&
b0001111011 )
b0100100011 *
b0111001011 +
b1001110011 ,
#4540
0&
#4550
b100 $
1&
b0001111100 )
b0100100100 *
b0111001100 +
b1001110100 ,
#4560
0&
#4570
b000 #
b000 $
b01001 %
1&
b0000001001 )
b0010110001 *
b0101011001 +
b1000000001 ,
#4580
0&
#4590
b001 $
1&
b0000001010 )
b0010110010 *
b0101011010 +
b1000000010 ,
#4600
0&
#4610
b010 $
1&
b0000001011 )
b0010110011 *
b0101011011 +
b1000000011 ,
#4620
0&
#4630
b011 $
1&
b0000001100 )
b0010110100 *
b0101011100 +
b1000000100 ,
#4640
0&
#4650
b100 $
1&
b0000001101 )
b0010110101 *
b0101011101 +
b1000000101 ,
#4660
0&
#4670
b001 #
b000 $
1&
b0000100101 )
b0011001101 *
b0101110101 +
b1000011101 ,
#4680
0&
#4690
b001 $
1&
b0000100110 )
b0011001110 *
b0101110110 +
b1000011110 ,
#4700
0&
#4710
b010 $
1&
b0000100111 )
b0011001111 *
b0101110111 +
b1000011111 ,
#4720
0&
#4730
b011 $
1&
b0000101000 )
b0011010000 *
b0101111000 +
b1000100000 ,
#4740
0&
#4750
b100 $
1&
b0000101001 )
b0011010001 *
b0101111001 +
b1000100001 ,
#4760
0&
#4770
b010 #
b000 $
1&
b0001000001 )
b0011101001 *
b0110010001 +
b1000111001 ,
#4780
0&
#4790
b001 $
1&
b0001000010 )
b0011101010 *
b0110010010 +
b1000111010 ,
#4800
0&
#4810
b010 $
1&
b0001000011 )
b0011101011 *
b0110010011 +
b1000111011 ,
#4820
0&
#4830
b011 $
1&
b0001000100 )
b0011101100 *
b0110010100 +
b1000111100 ,
#4840
0&
#4850
b100 $
1&
b0001000101 )
b0011101101 *
b0110010101 +
b1000111101 ,
#4860
0&
#4870
b011 #
b000 $
1&
b0001011101 )
b0100000101 *
b0110101101 +
b1001010101 ,
#4880
0&
#4890
b001 $
1&
b0001011110 )
b0100000110 *
b0110101110 +
b1001010110 ,
#4900
0&
#4910
b010 $
1&
b0001011111 )
b0100000111 *
b0110101111 +
b1001010111 ,
#4920
0&
#4930
b011 $
1&
b0001100000 )
b0100001000 *
b0110110000 +
b1001011000 ,
#4940
0&
#4950
b100 $
1&
b0001100001 )
b0100001001 *
b0110110001 +
b1001011001 ,
#4960
0&
#4970
b100 #
b000 $
1&
b0001111001 )
b0100100001 *
b0111001001 +
b1001110001 ,
#4980
0&
#4990
b001 $
1&
b0001111010 )
b0100100010 *
b0111001010 +
b1001110010 ,
#5000
0&
#5010
b010 $
1&
b0001111011 )
b0100100011 *
b0111001011 +
b1001110011 ,
#5020
0&
#5030
b011 $
1&
b0001111100 )
b0100100100 *
b0111001100 +
b1001110100 ,
#5040
0&
#5050
b100 $
1&
b0001111101 )
b0100100101 *
b0111001101 +
b1001110101 ,
#5060
0&
#5070
b000 #
b000 $
b01010 %
1&
b0000001010 )
b0010110010 *
b0101011010 +
b1000000010 ,
#5080
0&
