hardware/mem_counter_test/P1_mem_read.sv
//P1_mem_read is responsible for one conv2 output image and uses two output addresses in parallel. Each processes half of the image, the offset between addresses is 12 * 8 / 2 = 48
// counter/addresser for pooling 1 layer output memory read
module P1_mem_read (input logic clk, reset, enable,
                        output logic [7:0] addr0, addr1,
                        output logic done);
    //kernel row and column count
    logic [2:0] rowcount, columncount;
    //counter for position within image row
    logic [2:0] i_count;

    always_ff @(posedge clk or posedge reset) begin
        if (reset == 1'b1) begin
            addr0 <= 8'b00000000;
            addr1 <= 8'b00110000;
            i_count <= 3'b000;
        end
        else if (enable == 1'b1 && done == 1'b0) begin
            if (i_count == 3'b111 && rowcount == 3'b100 && columncount == 3'b100) begin
                //done with applying the kernel over an entire image row, go to the next row
                //Move addresses 4 rows up, 11 pixels back and 1 row down, i.e. -47
                i_count <= 3'b000;
                columncount <= 3'b000;
                rowcount <= 3'b000;
                addr0 <= addr0 - 8'b00101111;
                addr1 <= addr1 - 8'b00101111;
            end
            else if (rowcount == 3'b100 && columncount == 3'b100) begin
                //done with a position for the kernel, move forward to the next position. Move 4 rows up, 4 pixels back and 1 pixel forward, i.e. -51
                columncount <= 3'b000;
                rowcount <= 3'b000;
                addr0 <= addr0 - 8'b00110011;
                addr1 <= addr1 - 8'b00110011;
                i_count <= i_count + 3'b001;
            end
            else if (columncount == 3'b100) begin
                //kernel row has been processed, move addresses one row down and 4 pixels back, i.e. + 8
                columncount <= 3'b000;
                rowcount <= rowcount + 3'b001;
                addr0 <= addr0 + 8'b00001000;
                addr1 <= addr1 + 8'b00001000;
            end
            else begin
                addr0 <= addr0 + 8'b00000001;
                addr1 <= addr1 + 8'b00000001;
                columncount <= columncount + 3'b001;
            end
        end
    end
    
    always_comb begin
        if(addr1 == 8'b10001111) begin
            done = 1'b1;
        end
    end

endmodule

hardware/mem_counter_test/P1_mem_read.vcd
$version Generated by VerilatedVcd $end
$date Thu May  5 10:34:27 2022
 $end
$timescale   1ns $end

 $scope module TOP $end
  $var wire  8 ) addr0 [7:0] $end
  $var wire  8 * addr1 [7:0] $end
  $var wire  1 & clk $end
  $var wire  1 + done $end
  $var wire  1 ( enable $end
  $var wire  1 ' reset $end
  $scope module P1_mem_read $end
   $var wire  8 ) addr0 [7:0] $end
   $var wire  8 * addr1 [7:0] $end
   $var wire  1 & clk $end
   $var wire  3 $ columncount [2:0] $end
   $var wire  1 + done $end
   $var wire  1 ( enable $end
   $var wire  3 % i_count [2:0] $end
   $var wire  1 ' reset $end
   $var wire  3 # rowcount [2:0] $end
  $upscope $end
 $upscope $end
$enddefinitions $end


#0
b000 #
b000 $
b000 %
0&
0'
0(
b00000000 )
b00000000 *
0+
#10
1&
#20
0&
1'
b00110000 *
#30
1&
#40
0&
#50
1&
#60
0&
0'
#70
1&
#80
0&
1(
#90
b001 $
1&
b00000001 )
b00110001 *
#90
#100
0&
#110
b010 $
1&
b00000010 )
b00110010 *
#120
0&
#130
b011 $
1&
b00000011 )
b00110011 *
#140
0&
#150
b100 $
1&
b00000100 )
b00110100 *
#160
0&
#170
b001 #
b000 $
1&
b00001100 )
b00111100 *
#180
0&
#190
b001 $
1&
b00001101 )
b00111101 *
#200
0&
#210
b010 $
1&
b00001110 )
b00111110 *
#220
0&
#230
b011 $
1&
b00001111 )
b00111111 *
#240
0&
#250
b100 $
1&
b00010000 )
b01000000 *
#260
0&
#270
b010 #
b000 $
1&
b00011000 )
b01001000 *
#280
0&
#290
b001 $
1&
b00011001 )
b01001001 *
#300
0&
#310
b010 $
1&
b00011010 )
b01001010 *
#320
0&
#330
b011 $
1&
b00011011 )
b01001011 *
#340
0&
#350
b100 $
1&
b00011100 )
b01001100 *
#360
0&
#370
b011 #
b000 $
1&
b00100100 )
b01010100 *
#380
0&
#390
b001 $
1&
b00100101 )
b01010101 *
#400
0&
#410
b010 $
1&
b00100110 )
b01010110 *
#420
0&
#430
b011 $
1&
b00100111 )
b01010111 *
#440
0&
#450
b100 $
1&
b00101000 )
b01011000 *
#460
0&
#470
b100 #
b000 $
1&
b00110000 )
b01100000 *
#480
0&
#490
b001 $
1&
b00110001 )
b01100001 *
#500
0&
#510
b010 $
1&
b00110010 )
b01100010 *
#520
0&
#530
b011 $
1&
b00110011 )
b01100011 *
#540
0&
#550
b100 $
1&
b00110100 )
b01100100 *
#560
0&
#570
b000 #
b000 $
b001 %
1&
b00000001 )
b00110001 *
#580
0&
#590
b001 $
1&
b00000010 )
b00110010 *
#600
0&
#610
b010 $
1&
b00000011 )
b00110011 *
#620
0&
#630
b011 $
1&
b00000100 )
b00110100 *
#640
0&
#650
b100 $
1&
b00000101 )
b00110101 *
#660
0&
#670
b001 #
b000 $
1&
b00001101 )
b00111101 *
#680
0&
#690
b001 $
1&
b00001110 )
b00111110 *
#700
0&
#710
b010 $
1&
b00001111 )
b00111111 *
#720
0&
#730
b011 $
1&
b00010000 )
b01000000 *
#740
0&
#750
b100 $
1&
b00010001 )
b01000001 *
#760
0&
#770
b010 #
b000 $
1&
b00011001 )
b01001001 *
#780
0&
#790
b001 $
1&
b00011010 )
b01001010 *
#800
0&
#810
b010 $
1&
b00011011 )
b01001011 *
#820
0&
#830
b011 $
1&
b00011100 )
b01001100 *
#840
0&
#850
b100 $
1&
b00011101 )
b01001101 *
#860
0&
#870
b011 #
b000 $
1&
b00100101 )
b01010101 *
#880
0&
#890
b001 $
1&
b00100110 )
b01010110 *
#900
0&
#910
b010 $
1&
b00100111 )
b01010111 *
#920
0&
#930
b011 $
1&
b00101000 )
b01011000 *
#940
0&
#950
b100 $
1&
b00101001 )
b01011001 *
#960
0&
#970
b100 #
b000 $
1&
b00110001 )
b01100001 *
#980
0&
#990
b001 $
1&
b00110010 )
b01100010 *
#1000
0&
#1010
b010 $
1&
b00110011 )
b01100011 *
#1020
0&
#1030
b011 $
1&
b00110100 )
b01100100 *
#1040
0&
#1050
b100 $
1&
b00110101 )
b01100101 *
#1060
0&
#1070
b000 #
b000 $
b010 %
1&
b00000010 )
b00110010 *
#1080
0&
#1090
b001 $
1&
b00000011 )
b00110011 *
#1100
0&
#1110
b010 $
1&
b00000100 )
b00110100 *
#1120
0&
#1130
b011 $
1&
b00000101 )
b00110101 *
#1140
0&
#1150
b100 $
1&
b00000110 )
b00110110 *
#1160
0&
#1170
b001 #
b000 $
1&
b00001110 )
b00111110 *
#1180
0&
#1190
b001 $
1&
b00001111 )
b00111111 *
#1200
0&
#1210
b010 $
1&
b00010000 )
b01000000 *
#1220
0&
#1230
b011 $
1&
b00010001 )
b01000001 *
#1240
0&
#1250
b100 $
1&
b00010010 )
b01000010 *
#1260
0&
#1270
b010 #
b000 $
1&
b00011010 )
b01001010 *
#1280
0&
#1290
b001 $
1&
b00011011 )
b01001011 *
#1300
0&
#1310
b010 $
1&
b00011100 )
b01001100 *
#1320
0&
#1330
b011 $
1&
b00011101 )
b01001101 *
#1340
0&
#1350
b100 $
1&
b00011110 )
b01001110 *
#1360
0&
#1370
b011 #
b000 $
1&
b00100110 )
b01010110 *
#1380
0&
#1390
b001 $
1&
b00100111 )
b01010111 *
#1400
0&
#1410
b010 $
1&
b00101000 )
b01011000 *
#1420
0&
#1430
b011 $
1&
b00101001 )
b01011001 *
#1440
0&
#1450
b100 $
1&
b00101010 )
b01011010 *
#1460
0&
#1470
b100 #
b000 $
1&
b00110010 )
b01100010 *
#1480
0&
#1490
b001 $
1&
b00110011 )
b01100011 *
#1500
0&
#1510
b010 $
1&
b00110100 )
b01100100 *
#1520
0&
#1530
b011 $
1&
b00110101 )
b01100101 *
#1540
0&
#1550
b100 $
1&
b00110110 )
b01100110 *
#1560
0&
#1570
b000 #
b000 $
b011 %
1&
b00000011 )
b00110011 *
#1580
0&
#1590
b001 $
1&
b00000100 )
b00110100 *
#1600
0&
#1610
b010 $
1&
b00000101 )
b00110101 *
#1620
0&
#1630
b011 $
1&
b00000110 )
b00110110 *
#1640
0&
#1650
b100 $
1&
b00000111 )
b00110111 *
#1660
0&
#1670
b001 #
b000 $
1&
b00001111 )
b00111111 *
#1680
0&
#1690
b001 $
1&
b00010000 )
b01000000 *
#1700
0&
#1710
b010 $
1&
b00010001 )
b01000001 *
#1720
0&
#1730
b011 $
1&
b00010010 )
b01000010 *
#1740
0&
#1750
b100 $
1&
b00010011 )
b01000011 *
#1760
0&
#1770
b010 #
b000 $
1&
b00011011 )
b01001011 *
#1780
0&
#1790
b001 $
1&
b00011100 )
b01001100 *
#1800
0&
#1810
b010 $
1&
b00011101 )
b01001101 *
#1820
0&
#1830
b011 $
1&
b00011110 )
b01001110 *
#1840
0&
#1850
b100 $
1&
b00011111 )
b01001111 *
#1860
0&
#1870
b011 #
b000 $
1&
b00100111 )
b01010111 *
#1880
0&
#1890
b001 $
1&
b00101000 )
b01011000 *
#1900
0&
#1910
b010 $
1&
b00101001 )
b01011001 *
#1920
0&
#1930
b011 $
1&
b00101010 )
b01011010 *
#1940
0&
#1950
b100 $
1&
b00101011 )
b01011011 *
#1960
0&
#1970
b100 #
b000 $
1&
b00110011 )
b01100011 *
#1980
0&
#1990
b001 $
1&
b00110100 )
b01100100 *
#2000
0&
#2010
b010 $
1&
b00110101 )
b01100101 *
#2020
0&
#2030
b011 $
1&
b00110110 )
b01100110 *
#2040
0&
#2050
b100 $
1&
b00110111 )
b01100111 *
#2060
0&
#2070
b000 #
b000 $
b100 %
1&
b00000100 )
b00110100 *
#2080
0&
#2090
b001 $
1&
b00000101 )
b00110101 *
#2100
0&
#2110
b010 $
1&
b00000110 )
b00110110 *
#2120
0&
#2130
b011 $
1&
b00000111 )
b00110111 *
#2140
0&
#2150
b100 $
1&
b00001000 )
b00111000 *
#2160
0&
#2170
b001 #
b000 $
1&
b00010000 )
b01000000 *
#2180
0&
#2190
b001 $
1&
b00010001 )
b01000001 *
#2200
0&
#2210
b010 $
1&
b00010010 )
b01000010 *
#2220
0&
#2230
b011 $
1&
b00010011 )
b01000011 *
#2240
0&
#2250
b100 $
1&
b00010100 )
b01000100 *
#2260
0&
#2270
b010 #
b000 $
1&
b00011100 )
b01001100 *
#2280
0&
#2290
b001 $
1&
b00011101 )
b01001101 *
#2300
0&
#2310
b010 $
1&
b00011110 )
b01001110 *
#2320
0&
#2330
b011 $
1&
b00011111 )
b01001111 *
#2340
0&
#2350
b100 $
1&
b00100000 )
b01010000 *
#2360
0&
#2370
b011 #
b000 $
1&
b00101000 )
b01011000 *
#2380
0&
#2390
b001 $
1&
b00101001 )
b01011001 *
#2400
0&
#2410
b010 $
1&
b00101010 )
b01011010 *
#2420
0&
#2430
b011 $
1&
b00101011 )
b01011011 *
#2440
0&
#2450
b100 $
1&
b00101100 )
b01011100 *
#2460
0&
#2470
b100 #
b000 $
1&
b00110100 )
b01100100 *
#2480
0&
#2490
b001 $
1&
b00110101 )
b01100101 *
#2500
0&
#2510
b010 $
1&
b00110110 )
b01100110 *
#2520
0&
#2530
b011 $
1&
b00110111 )
b01100111 *
#2540
0&
#2550
b100 $
1&
b00111000 )
b01101000 *
#2560
0&
#2570
b000 #
b000 $
b101 %
1&
b00000101 )
b00110101 *
#2580
0&
#2590
b001 $
1&
b00000110 )
b00110110 *
#2600
0&
#2610
b010 $
1&
b00000111 )
b00110111 *
#2620
0&
#2630
b011 $
1&
b00001000 )
b00111000 *
#2640
0&
#2650
b100 $
1&
b00001001 )
b00111001 *
#2660
0&
#2670
b001 #
b000 $
1&
b00010001 )
b01000001 *
#2680
0&
#2690
b001 $
1&
b00010010 )
b01000010 *
#2700
0&
#2710
b010 $
1&
b00010011 )
b01000011 *
#2720
0&
#2730
b011 $
1&
b00010100 )
b01000100 *
#2740
0&
#2750
b100 $
1&
b00010101 )
b01000101 *
#2760
0&
#2770
b010 #
b000 $
1&
b00011101 )
b01001101 *
#2780
0&
#2790
b001 $
1&
b00011110 )
b01001110 *
#2800
0&
#2810
b010 $
1&
b00011111 )
b01001111 *
#2820
0&
#2830
b011 $
1&
b00100000 )
b01010000 *
#2840
0&
#2850
b100 $
1&
b00100001 )
b01010001 *
#2860
0&
#2870
b011 #
b000 $
1&
b00101001 )
b01011001 *
#2880
0&
#2890
b001 $
1&
b00101010 )
b01011010 *
#2900
0&
#2910
b010 $
1&
b00101011 )
b01011011 *
#2920
0&
#2930
b011 $
1&
b00101100 )
b01011100 *
#2940
0&
#2950
b100 $
1&
b00101101 )
b01011101 *
#2960
0&
#2970
b100 #
b000 $
1&
b00110101 )
b01100101 *
#2980
0&
#2990
b001 $
1&
b00110110 )
b01100110 *
#3000
0&
#3010
b010 $
1&
b00110111 )
b01100111 *
#3020
0&
#3030
b011 $
1&
b00111000 )
b01101000 *
#3040
0&
#3050
b100 $
1&
b00111001 )
b01101001 *
#3060
0&
#3070
b000 #
b000 $
b110 %
1&
b00000110 )
b00110110 *
#3080
0&
#3090
b001 $
1&
b00000111 )
b00110111 *
#3100
0&
#3110
b010 $
1&
b00001000 )
b00111000 *
#3120
0&
#3130
b011 $
1&
b00001001 )
b00111001 *
#3140
0&
#3150
b100 $
1&
b00001010 )
b00111010 *
#3160
0&
#3170
b001 #
b000 $
1&
b00010010 )
b01000010 *
#3180
0&
#3190
b001 $
1&
b00010011 )
b01000011 *
#3200
0&
#3210
b010 $
1&
b00010100 )
b01000100 *
#3220
0&
#3230
b011 $
1&
b00010101 )
b01000101 *
#3240
0&
#3250
b100 $
1&
b00010110 )
b01000110 *
#3260
0&
#3270
b010 #
b000 $
1&
b00011110 )
b01001110 *
#3280
0&
#3290
b001 $
1&
b00011111 )
b01001111 *
#3300
0&
#3310
b010 $
1&
b00100000 )
b01010000 *
#3320
0&
#3330
b011 $
1&
b00100001 )
b01010001 *
#3340
0&
#3350
b100 $
1&
b00100010 )
b01010010 *
#3360
0&
#3370
b011 #
b000 $
1&
b00101010 )
b01011010 *
#3380
0&
#3390
b001 $
1&
b00101011 )
b01011011 *
#3400
0&
#3410
b010 $
1&
b00101100 )
b01011100 *
#3420
0&
#3430
b011 $
1&
b00101101 )
b01011101 *
#3440
0&
#3450
b100 $
1&
b00101110 )
b01011110 *
#3460
0&
#3470
b100 #
b000 $
1&
b00110110 )
b01100110 *
#3480
0&
#3490
b001 $
1&
b00110111 )
b01100111 *
#3500
0&
#3510
b010 $
1&
b00111000 )
b01101000 *
#3520
0&
#3530
b011 $
1&
b00111001 )
b01101001 *
#3540
0&
#3550
b100 $
1&
b00111010 )
b01101010 *
#3560
0&
#3570
b000 #
b000 $
b111 %
1&
b00000111 )
b00110111 *
#3580
0&
#3590
b001 $
1&
b00001000 )
b00111000 *
#3600
0&
#3610
b010 $
1&
b00001001 )
b00111001 *
#3620
0&
#3630
b011 $
1&
b00001010 )
b00111010 *
#3640
0&
#3650
b100 $
1&
b00001011 )
b00111011 *
#3660
0&
#3670
b001 #
b000 $
1&
b00010011 )
b01000011 *
#3680
0&
#3690
b001 $
1&
b00010100 )
b01000100 *
#3700
0&
#3710
b010 $
1&
b00010101 )
b01000101 *
#3720
0&
#3730
b011 $
1&
b00010110 )
b01000110 *
#3740
0&
#3750
b100 $
1&
b00010111 )
b01000111 *
#3760
0&
#3770
b010 #
b000 $
1&
b00011111 )
b01001111 *
#3780
0&
#3790
b001 $
1&
b00100000 )
b01010000 *
#3800
0&
#3810
b010 $
1&
b00100001 )
b01010001 *
#3820
0&
#3830
b011 $
1&
b00100010 )
b01010010 *
#3840
0&
#3850
b100 $
1&
b00100011 )
b01010011 *
#3860
0&
#3870
b011 #
b000 $
1&
b00101011 )
b01011011 *
#3880
0&
#3890
b001 $
1&
b00101100 )
b01011100 *
#3900
0&
#3910
b010 $
1&
b00101101 )
b01011101 *
#3920
0&
#3930
b011 $
1&
b00101110 )
b01011110 *
#3940
0&
#3950
b100 $
1&
b00101111 )
b01011111 *
#3960
0&
#3970
b100 #
b000 $
1&
b00110111 )
b01100111 *
#3980
0&
#3990
b001 $
1&
b00111000 )
b01101000 *
#4000
0&
#4010
b010 $
1&
b00111001 )
b01101001 *
#4020
0&
#4030
b011 $
1&
b00111010 )
b01101010 *
#4040
0&
#4050
b100 $
1&
b00111011 )
b01101011 *
#4060
0&
#4070
b000 #
b000 $
b000 %
1&
b00001100 )
b00111100 *
#4080
0&
#4090
b001 $
1&
b00001101 )
b00111101 *
#4100
0&
#4110
b010 $
1&
b00001110 )
b00111110 *
#4120
0&
#4130
b011 $
1&
b00001111 )
b00111111 *
#4140
0&
#4150
b100 $
1&
b00010000 )
b01000000 *
#4160
0&
#4170
b001 #
b000 $
1&
b00011000 )
b01001000 *
#4180
0&
#4190
b001 $
1&
b00011001 )
b01001001 *
#4200
0&
#4210
b010 $
1&
b00011010 )
b01001010 *
#4220
0&
#4230
b011 $
1&
b00011011 )
b01001011 *
#4240
0&
#4250
b100 $
1&
b00011100 )
b01001100 *
#4260
0&
#4270
b010 #
b000 $
1&
b00100100 )
b01010100 *
#4280
0&
#4290
b001 $
1&
b00100101 )
b01010101 *
#4300
0&
#4310
b010 $
1&
b00100110 )
b01010110 *
#4320
0&
#4330
b011 $
1&
b00100111 )
b01010111 *
#4340
0&
#4350
b100 $
1&
b00101000 )
b01011000 *
#4360
0&
#4370
b011 #
b000 $
1&
b00110000 )
b01100000 *
#4380
0&
#4390
b001 $
1&
b00110001 )
b01100001 *
#4400
0&
#4410
b010 $
1&
b00110010 )
b01100010 *
#4420
0&
#4430
b011 $
1&
b00110011 )
b01100011 *
#4440
0&
#4450
b100 $
1&
b00110100 )
b01100100 *
#4460
0&
#4470
b100 #
b000 $
1&
b00111100 )
b01101100 *
#4480
0&
#4490
b001 $
1&
b00111101 )
b01101101 *
#4500
0&
#4510
b010 $
1&
b00111110 )
b01101110 *
#4520
0&
#4530
b011 $
1&
b00111111 )
b01101111 *
#4540
0&
#4550
b100 $
1&
b01000000 )
b01110000 *
#4560
0&
#4570
b000 #
b000 $
b001 %
1&
b00001101 )
b00111101 *
#4580
0&
#4590
b001 $
1&
b00001110 )
b00111110 *
#4600
0&
#4610
b010 $
1&
b00001111 )
b00111111 *
#4620
0&
#4630
b011 $
1&
b00010000 )
b01000000 *
#4640
0&
#4650
b100 $
1&
b00010001 )
b01000001 *
#4660
0&
#4670
b001 #
b000 $
1&
b00011001 )
b01001001 *
#4680
0&
#4690
b001 $
1&
b00011010 )
b01001010 *
#4700
0&
#4710
b010 $
1&
b00011011 )
b01001011 *
#4720
0&
#4730
b011 $
1&
b00011100 )
b01001100 *
#4740
0&
#4750
b100 $
1&
b00011101 )
b01001101 *
#4760
0&
#4770
b010 #
b000 $
1&
b00100101 )
b01010101 *
#4780
0&
#4790
b001 $
1&
b00100110 )
b01010110 *
#4800
0&
#4810
b010 $
1&
b00100111 )
b01010111 *
#4820
0&
#4830
b011 $
1&
b00101000 )
b01011000 *
#4840
0&
#4850
b100 $
1&
b00101001 )
b01011001 *
#4860
0&
#4870
b011 #
b000 $
1&
b00110001 )
b01100001 *
#4880
0&
#4890
b001 $
1&
b00110010 )
b01100010 *
#4900
0&
#4910
b010 $
1&
b00110011 )
b01100011 *
#4920
0&
#4930
b011 $
1&
b00110100 )
b01100100 *
#4940
0&
#4950
b100 $
1&
b00110101 )
b01100101 *
#4960
0&
#4970
b100 #
b000 $
1&
b00111101 )
b01101101 *
#4980
0&
#4990
b001 $
1&
b00111110 )
b01101110 *
#5000
0&
#5010
b010 $
1&
b00111111 )
b01101111 *
#5020
0&
#5030
b011 $
1&
b01000000 )
b01110000 *
#5040
0&
#5050
b100 $
1&
b01000001 )
b01110001 *
#5060
0&
#5070
b000 #
b000 $
b010 %
1&
b00001110 )
b00111110 *
#5080
0&
#5090
b001 $
1&
b00001111 )
b00111111 *
#5100
0&
#5110
b010 $
1&
b00010000 )
b01000000 *
#5120
0&
#5130
b011 $
1&
b00010001 )
b01000001 *
#5140
0&
#5150
b100 $
1&
b00010010 )
b01000010 *
#5160
0&
#5170
b001 #
b000 $
1&
b00011010 )
b01001010 *
#5180
0&
#5190
b001 $
1&
b00011011 )
b01001011 *
#5200
0&
#5210
b010 $
1&
b00011100 )
b01001100 *
#5220
0&
#5230
b011 $
1&
b00011101 )
b01001101 *
#5240
0&
#5250
b100 $
1&
b00011110 )
b01001110 *
#5260
0&
#5270
b010 #
b000 $
1&
b00100110 )
b01010110 *
#5280
0&
#5290
b001 $
1&
b00100111 )
b01010111 *
#5300
0&
#5310
b010 $
1&
b00101000 )
b01011000 *
#5320
0&
#5330
b011 $
1&
b00101001 )
b01011001 *
#5340
0&
#5350
b100 $
1&
b00101010 )
b01011010 *
#5360
0&
#5370
b011 #
b000 $
1&
b00110010 )
b01100010 *
#5380
0&
#5390
b001 $
1&
b00110011 )
b01100011 *
#5400
0&
#5410
b010 $
1&
b00110100 )
b01100100 *
#5420
0&
#5430
b011 $
1&
b00110101 )
b01100101 *
#5440
0&
#5450
b100 $
1&
b00110110 )
b01100110 *
#5460
0&
#5470
b100 #
b000 $
1&
b00111110 )
b01101110 *
#5480
0&
#5490
b001 $
1&
b00111111 )
b01101111 *
#5500
0&
#5510
b010 $
1&
b01000000 )
b01110000 *
#5520
0&
#5530
b011 $
1&
b01000001 )
b01110001 *
#5540
0&
#5550
b100 $
1&
b01000010 )
b01110010 *
#5560
0&
#5570
b000 #
b000 $
b011 %
1&
b00001111 )
b00111111 *
#5580
0&
#5590
b001 $
1&
b00010000 )
b01000000 *
#5600
0&
#5610
b010 $
1&
b00010001 )
b01000001 *
#5620
0&
#5630
b011 $
1&
b00010010 )
b01000010 *
#5640
0&
#5650
b100 $
1&
b00010011 )
b01000011 *
#5660
0&
#5670
b001 #
b000 $
1&
b00011011 )
b01001011 *
#5680
0&
#5690
b001 $
1&
b00011100 )
b01001100 *
#5700
0&
#5710
b010 $
1&
b00011101 )
b01001101 *
#5720
0&
#5730
b011 $
1&
b00011110 )
b01001110 *
#5740
0&
#5750
b100 $
1&
b00011111 )
b01001111 *
#5760
0&
#5770
b010 #
b000 $
1&
b00100111 )
b01010111 *
#5780
0&
#5790
b001 $
1&
b00101000 )
b01011000 *
#5800
0&
#5810
b010 $
1&
b00101001 )
b01011001 *
#5820
0&
#5830
b011 $
1&
b00101010 )
b01011010 *
#5840
0&
#5850
b100 $
1&
b00101011 )
b01011011 *
#5860
0&
#5870
b011 #
b000 $
1&
b00110011 )
b01100011 *
#5880
0&
#5890
b001 $
1&
b00110100 )
b01100100 *
#5900
0&
#5910
b010 $
1&
b00110101 )
b01100101 *
#5920
0&
#5930
b011 $
1&
b00110110 )
b01100110 *
#5940
0&
#5950
b100 $
1&
b00110111 )
b01100111 *
#5960
0&
#5970
b100 #
b000 $
1&
b00111111 )
b01101111 *
#5980
0&
#5990
b001 $
1&
b01000000 )
b01110000 *
#6000
0&
#6010
b010 $
1&
b01000001 )
b01110001 *
#6020
0&
#6030
b011 $
1&
b01000010 )
b01110010 *
#6040
0&
#6050
b100 $
1&
b01000011 )
b01110011 *
#6060
0&
#6070
b000 #
b000 $
b100 %
1&
b00010000 )
b01000000 *
#6080
0&
#6090
b001 $
1&
b00010001 )
b01000001 *
#6100
0&
#6110
b010 $
1&
b00010010 )
b01000010 *
#6120
0&
#6130
b011 $
1&
b00010011 )
b01000011 *
#6140
0&
#6150
b100 $
1&
b00010100 )
b01000100 *
#6160
0&
#6170
b001 #
b000 $
1&
b00011100 )
b01001100 *
#6180
0&
#6190
b001 $
1&
b00011101 )
b01001101 *
#6200
0&
#6210
b010 $
1&
b00011110 )
b01001110 *
#6220
0&
#6230
b011 $
1&
b00011111 )
b01001111 *
#6240
0&
#6250
b100 $
1&
b00100000 )
b01010000 *
#6260
0&
#6270
b010 #
b000 $
1&
b00101000 )
b01011000 *
#6280
0&
#6290
b001 $
1&
b00101001 )
b01011001 *
#6300
0&
#6310
b010 $
1&
b00101010 )
b01011010 *
#6320
0&
#6330
b011 $
1&
b00101011 )
b01011011 *
#6340
0&
#6350
b100 $
1&
b00101100 )
b01011100 *
#6360
0&
#6370
b011 #
b000 $
1&
b00110100 )
b01100100 *
#6380
0&
#6390
b001 $
1&
b00110101 )
b01100101 *
#6400
0&
#6410
b010 $
1&
b00110110 )
b01100110 *
#6420
0&
#6430
b011 $
1&
b00110111 )
b01100111 *
#6440
0&
#6450
b100 $
1&
b00111000 )
b01101000 *
#6460
0&
#6470
b100 #
b000 $
1&
b01000000 )
b01110000 *
#6480
0&
#6490
b001 $
1&
b01000001 )
b01110001 *
#6500
0&
#6510
b010 $
1&
b01000010 )
b01110010 *
#6520
0&
#6530
b011 $
1&
b01000011 )
b01110011 *
#6540
0&
#6550
b100 $
1&
b01000100 )
b01110100 *
#6560
0&
#6570
b000 #
b000 $
b101 %
1&
b00010001 )
b01000001 *
#6580
0&
#6590
b001 $
1&
b00010010 )
b01000010 *
#6600
0&
#6610
b010 $
1&
b00010011 )
b01000011 *
#6620
0&
#6630
b011 $
1&
b00010100 )
b01000100 *
#6640
0&
#6650
b100 $
1&
b00010101 )
b01000101 *
#6660
0&
#6670
b001 #
b000 $
1&
b00011101 )
b01001101 *
#6680
0&
#6690
b001 $
1&
b00011110 )
b01001110 *
#6700
0&
#6710
b010 $
1&
b00011111 )
b01001111 *
#6720
0&
#6730
b011 $
1&
b00100000 )
b01010000 *
#6740
0&
#6750
b100 $
1&
b00100001 )
b01010001 *
#6760
0&
#6770
b010 #
b000 $
1&
b00101001 )
b01011001 *
#6780
0&
#6790
b001 $
1&
b00101010 )
b01011010 *
#6800
0&
#6810
b010 $
1&
b00101011 )
b01011011 *
#6820
0&
#6830
b011 $
1&
b00101100 )
b01011100 *
#6840
0&
#6850
b100 $
1&
b00101101 )
b01011101 *
#6860
0&
#6870
b011 #
b000 $
1&
b00110101 )
b01100101 *
#6880
0&
#6890
b001 $
1&
b00110110 )
b01100110 *
#6900
0&
#6910
b010 $
1&
b00110111 )
b01100111 *
#6920
0&
#6930
b011 $
1&
b00111000 )
b01101000 *
#6940
0&
#6950
b100 $
1&
b00111001 )
b01101001 *
#6960
0&
#6970
b100 #
b000 $
1&
b01000001 )
b01110001 *
#6980
0&
#6990
b001 $
1&
b01000010 )
b01110010 *
#7000
0&
#7010
b010 $
1&
b01000011 )
b01110011 *
#7020
0&
#7030
b011 $
1&
b01000100 )
b01110100 *
#7040
0&
#7050
b100 $
1&
b01000101 )
b01110101 *
#7060
0&
#7070
b000 #
b000 $
b110 %
1&
b00010010 )
b01000010 *
#7080
0&
#7090
b001 $
1&
b00010011 )
b01000011 *
#7100
0&
#7110
b010 $
1&
b00010100 )
b01000100 *
#7120
0&
#7130
b011 $
1&
b00010101 )
b01000101 *
#7140
0&
#7150
b100 $
1&
b00010110 )
b01000110 *
#7160
0&
#7170
b001 #
b000 $
1&
b00011110 )
b01001110 *
#7180
0&
#7190
b001 $
1&
b00011111 )
b01001111 *
#7200
0&
#7210
b010 $
1&
b00100000 )
b01010000 *
#7220
0&
#7230
b011 $
1&
b00100001 )
b01010001 *
#7240
0&
#7250
b100 $
1&
b00100010 )
b01010010 *
#7260
0&
#7270
b010 #
b000 $
1&
b00101010 )
b01011010 *
#7280
0&
#7290
b001 $
1&
b00101011 )
b01011011 *
#7300
0&
#7310
b010 $
1&
b00101100 )
b01011100 *
#7320
0&
#7330
b011 $
1&
b00101101 )
b01011101 *
#7340
0&
#7350
b100 $
1&
b00101110 )
b01011110 *
#7360
0&
#7370
b011 #
b000 $
1&
b00110110 )
b01100110 *
#7380
0&
#7390
b001 $
1&
b00110111 )
b01100111 *
#7400
0&
#7410
b010 $
1&
b00111000 )
b01101000 *
#7420
0&
#7430
b011 $
1&
b00111001 )
b01101001 *
#7440
0&
#7450
b100 $
1&
b00111010 )
b01101010 *
#7460
0&
#7470
b100 #
b000 $
1&
b01000010 )
b01110010 *
#7480
0&
#7490
b001 $
1&
b01000011 )
b01110011 *
#7500
0&
#7510
b010 $
1&
b01000100 )
b01110100 *
#7520
0&
#7530
b011 $
1&
b01000101 )
b01110101 *
#7540
0&
#7550
b100 $
1&
b01000110 )
b01110110 *
#7560
0&
#7570
b000 #
b000 $
b111 %
1&
b00010011 )
b01000011 *
#7580
0&
#7590
b001 $
1&
b00010100 )
b01000100 *
#7600
0&
#7610
b010 $
1&
b00010101 )
b01000101 *
#7620
0&
#7630
b011 $
1&
b00010110 )
b01000110 *
#7640
0&
#7650
b100 $
1&
b00010111 )
b01000111 *
#7660
0&
#7670
b001 #
b000 $
1&
b00011111 )
b01001111 *
#7680
0&
#7690
b001 $
1&
b00100000 )
b01010000 *
#7700
0&
#7710
b010 $
1&
b00100001 )
b01010001 *
#7720
0&
#7730
b011 $
1&
b00100010 )
b01010010 *
#7740
0&
#7750
b100 $
1&
b00100011 )
b01010011 *
#7760
0&
#7770
b010 #
b000 $
1&
b00101011 )
b01011011 *
#7780
0&
#7790
b001 $
1&
b00101100 )
b01011100 *
#7800
0&
#7810
b010 $
1&
b00101101 )
b01011101 *
#7820
0&
#7830
b011 $
1&
b00101110 )
b01011110 *
#7840
0&
#7850
b100 $
1&
b00101111 )
b01011111 *
#7860
0&
#7870
b011 #
b000 $
1&
b00110111 )
b01100111 *
#7880
0&
#7890
b001 $
1&
b00111000 )
b01101000 *
#7900
0&
#7910
b010 $
1&
b00111001 )
b01101001 *
#7920
0&
#7930
b011 $
1&
b00111010 )
b01101010 *
#7940
0&
#7950
b100 $
1&
b00111011 )
b01101011 *
#7960
0&
#7970
b100 #
b000 $
1&
b01000011 )
b01110011 *
#7980
0&
#7990
b001 $
1&
b01000100 )
b01110100 *
#8000
0&
#8010
b010 $
1&
b01000101 )
b01110101 *
#8020
0&
#8030
b011 $
1&
b01000110 )
b01110110 *
#8040
0&
#8050
b100 $
1&
b01000111 )
b01110111 *
#8060
0&
