hardware/mem_counter_test/mem_counters.sv
// img_mem_write    : done
// img_mem_read     : 
// conv1_k_mem_read : done
// conv1_mem_write  : done
// conv1_mem_read   : done?
// P1_mem_write     : done
// P1_mem_read      : 
// conv2_k_mem_read : 
// conv2_mem_write  : 
// conv2_mem_read   : 
// P2_mem_write     : 
// P2_mem_read      : 
// fc_mem_read      : done

// counter/addresser for input image memory write (done) //NOT NEEDED
module img_mem_write (input logic clk, reset, enable, next, 
                      output logic [9:0] addr0,  
                      output logic done, ack);

    always_ff @(posedge clk or posedge reset) begin
        if (reset == 1'b1) begin
            addr0 <= 10'b0000000000;
        end
        else if (enable == 1'b1 && done == 1'b0) begin
            addr0 <= addr0 + 1;
            ack <= 1'b1;
        end
        else if(next == 1'b1 && ack == 1'b1) begin
            ack <= 1'b0;
        end
    end

    always_comb begin
        if(addr0 == 10'b1100001111) begin
            done = 1'b1;
        end
    end

endmodule

//img_mem_read is responsible for one conv1 output image and uses four output addresses in parallel. Each processes a quarter of the image, the offset between addresses is 28 * 24 / 4 = 168
// counter/addresser for input image memory read
module img_mem_read (input logic clk, reset, enable,
                     output logic [9:0] addr0, addr1, addr2, addr3, 
                     output logic done);

    //kernel row and column count
    logic [2:0] rowcount, columncount;
    //counter for position within image row
    logic [4:0] i_count;

    always_ff @(posedge clk or posedge reset) begin
        if (reset == 1'b1) begin
            addr0 <= 10'b0000000000;
            addr1 <= 10'b0010101000;
            addr2 <= 10'b0101010000;
            addr3 <= 10'b0111111000;
            i_count <= 5'b00000;
        end
        else if (enable == 1'b1 && done == 1'b0) begin
            if (i_count == 5'b10111 && rowcount == 3'b100 && columncount == 3'b100) begin
                //done with applying the kernel over an entire image row, go to the next row
                //Move addresses 4 rows up, 27 pixels back and 1 row down, i.e. -111
                i_count <= 5'b0000;
                columncount <= 3'b000;
                rowcount <= 3'b000;
                addr0 <= addr0 - 10'b0001101111;
                addr1 <= addr1 - 10'b0001101111;
                addr2 <= addr2 - 10'b0001101111;
                addr3 <= addr3 - 10'b0001101111;
            end
            else if (rowcount == 3'b100 && columncount == 3'b100) begin
                //done with a position for the kernel, move forward to the next position. Move 4 rows up, 4 pixels back and 1 pixel forward, i.e. -115
                columncount <= 3'b000;
                rowcount <= 3'b000;
                addr0 <= addr0 - 10'b0001110011;
                addr1 <= addr1 - 10'b0001110011;
                addr2 <= addr2 - 10'b0001110011;
                addr3 <= addr3 - 10'b0001110011;
                i_count <= i_count + 5'b00001;
            end
            else if (columncount == 3'b100) begin
                //kernel row has been processed, move addresses one row down and 4 pixels back, i.e. + 24
                columncount <= 3'b000;
                rowcount <= rowcount + 3'b001;
                addr0 <= addr0 + 10'b0000011000;
                addr1 <= addr1 + 10'b0000011000;
                addr2 <= addr2 + 10'b0000011000;
                addr3 <= addr3 + 10'b0000011000;
            end
            else begin
                addr0 <= addr0 + 10'b0000000001;
                addr1 <= addr1 + 10'b0000000001;
                addr2 <= addr2 + 10'b0000000001;
                addr3 <= addr3 + 10'b0000000001;
                columncount <= columncount + 3'b001;
            end
        end
    end

    always_comb begin
        if(addr3 == 10'b1100001111) begin
            done = 1'b1;
        end
    end

endmodule

// counter/addresser for Convolution 1 layer weight memory read (done)
module conv1_k_mem_read (input logic clk, reset, enable, 
                        output logic [5:0] addr0, addr1, 
                        output logic done);

    always_ff @(posedge clk or posedge reset) begin
        if (reset == 1'b1) begin
            addr0 <= 6'b000000;
            addr1 <= 6'b011001;
        end
        else if (enable == 1'b1 && done == 1'b0) begin
            addr0 <= addr0 + 6'b000001;
            addr1 <= addr1 + 6'b000001;
        end
    end

    always_comb begin
        if(addr1 == 6'b110001) begin
            done = 1'b1;
        end
    end

endmodule

// counter/addresser for Convolution 1 layer output memory write (done)
module conv1_mem_write (input logic clk, reset, enable,
                        output logic [9:0] addr0, addr1, 
                        output logic done);

    always_ff @(posedge clk or posedge reset) begin
        if (reset == 1'b1) begin
            addr0 <= 10'b0000000000;
            addr1 <= 10'b0010010000;
        end
        else if (enable == 1'b1 && done == 1'b0) begin
            addr0 <= addr0 + 10'b0000000001;
            addr1 <= addr1 + 10'b0000000001;
        end
    end

    always_comb begin
        if(addr1 == 10'b1000111111) begin
            done = 1'b1;
        end
    end

endmodule

// counter/addresser for Convolution 1 layer output memory read (done?)
module conv1_mem_read (input logic clk, reset, enable,
                        output logic [9:0] addr0, addr1, addr2, addr3, 
                        output logic done);

    logic [3:0] count;
    always_ff @(posedge clk or posedge reset) begin
        if (reset == 1'b1) begin
            addr0 <= 10'b0000000000;
            addr1 <= 10'b0000000001;
            addr2 <= 10'b0000011000;
            addr3 <= 10'b0000011001;
            count <= 4'b0000;
        end
        
        else if (enable == 1'b1 && done == 1'b0) begin
            if(count == 4'b1011) begin
                count <= 4'b0000;
                addr0 <= addr0 + 10'b0000011010;
                addr1 <= addr1 + 10'b0000011010;
                addr2 <= addr2 + 10'b0000011010;
                addr3 <= addr3 + 10'b0000011010;
            end
            else begin    
                addr0 <= addr0 + 10'b0000000010;
                addr1 <= addr1 + 10'b0000000010;
                addr2 <= addr2 + 10'b0000000010;
                addr3 <= addr3 + 10'b0000000010;
                count <= count + 4'b0001;
            end
        end
    end
    
    always_comb begin
        //stop when addr3 == 24^2 - 1, i.e. we have processed the entire image
        if(addr3 == 10'b1000111111) begin
            done = 1'b1;
        end
    end

endmodule

// counter/addresser for pooling 1 layer output memory write (done)
module P1_mem_write (input logic clk, reset, enable,
                        output logic [7:0] addr0, addr1,
                        output logic done);

    always_ff @(posedge clk or posedge reset) begin
        if (reset == 1'b1) begin
            addr0 <= 8'b00000000;
            addr1 <= 8'b01001000;
        end
        else if (enable == 1'b1 && done == 1'b0) begin
            addr0 <= addr0 + 8'b00000001;
            addr1 <= addr1 + 8'b00000001;
        end
    end
    
    always_comb begin
        //stop when addr1 == 12^2 - 1, i.e. we have processed the entire image
        if(addr1 == 8'b10001111) begin
            done = 1'b1;
        end
    end

endmodule

//P1_mem_read is responsible for one conv2 output image and uses two output addresses in parallel. Each processes half of the image, the offset between addresses is 12 * 8 / 2 = 48
// counter/addresser for pooling 1 layer output memory read
module P1_mem_read (input logic clk, reset, enable,
                        output logic [7:0] addr0, addr1,
                        output logic done);
    //kernel row and column count
    logic [2:0] rowcount, columncount;
    //counter for position within image row
    logic [2:0] i_count;

    always_ff @(posedge clk or posedge reset) begin
        if (reset == 1'b1) begin
            addr0 <= 8'b00000000;
            addr1 <= 8'b00110000;
            i_count <= 3'b000;
        end
        else if (enable == 1'b1 && done == 1'b0) begin
            if (i_count == 3'b111 && rowcount == 3'b100 && columncount == 3'b100) begin
                //done with applying the kernel over an entire image row, go to the next row
                //Move addresses 4 rows up, 11 pixels back and 1 row down, i.e. -47
                i_count <= 3'b000;
                columncount <= 3'b000;
                rowcount <= 3'b000;
                addr0 <= addr0 - 8'b00101111;
                addr1 <= addr1 - 8'b00101111;
            end
            else if (rowcount == 3'b100 && columncount == 3'b100) begin
                //done with a position for the kernel, move forward to the next position. Move 4 rows up, 4 pixels back and 1 pixel forward, i.e. -51
                columncount <= 3'b000;
                rowcount <= 3'b000;
                addr0 <= addr0 - 8'b00110011;
                addr1 <= addr1 - 8'b00110011;
                i_count <= i_count + 3'b001;
            end
            else if (columncount == 3'b100) begin
                //kernel row has been processed, move addresses one row down and 4 pixels back, i.e. + 8
                columncount <= 3'b000;
                rowcount <= rowcount + 3'b001;
                addr0 <= addr0 + 8'b00001000;
                addr1 <= addr1 + 8'b00001000;
            end
            else begin
                addr0 <= addr0 + 8'b00000001;
                addr1 <= addr1 + 8'b00000001;
                columncount <= columncount + 3'b001;
            end
        end
    end
    
    always_comb begin
        if(addr1 == 8'b10001111) begin
            done = 1'b1;
        end
    end

endmodule

//Module used to provide access to 6 kernels with two counters at once
// counter/addresser for Convolution 2 layer weight memory read
module conv2_k_mem_read (input logic clk, reset, enable,
                        output logic [7:0] addr0, addr1,
                        output logic done);

    always_ff @(posedge clk or posedge reset) begin
        if (reset == 1'b1) begin
            addr0 <= 8'b00000000;
            addr1 <= 8'b01001011;
        end
        else if (enable == 1'b1 && done == 1'b0) begin
            addr0 <= addr0 + 8'b00000001;
            addr1 <= addr1 + 8'b00000001;
        end
    end
    
    always_comb begin
        //Count until addr1 reaches end of 6th kernel, i.e. 6 * 25 - 1 = 149
        if(addr1 == 8'b10010101) begin
            done = 1'b1;
        end
    end

endmodule

//Go through an 8x8 output image 3 times
// counter/addresser for Convolution 2 layer output memory write
module conv2_mem_write (input logic clk, reset, enable,
                        output logic [5:0] addr0,
                        output logic done);
    logic [1:0] count;

    always_ff @(posedge clk or posedge reset) begin
        if (reset == 1'b1) begin
            addr0 <= 6'b000000;
            count <= 2'b00;
        end
        else if (enable == 1'b1 && done == 1'b0) begin
            if(addr0 == 6'b111111) begin
                count <= count + 2'b01;
                addr0 <= 6'b000000;
            end
            else begin
                addr0 <= addr0 + 6'b000001;
            end
        end
    end
    
    always_comb begin
        if(count == 2'b10 && addr0 == 6'b111111) begin
            done = 1'b1;
        end
    end

endmodule

// counter/addresser for Convolution 2 layer output memory read (done)
module conv2_mem_read (input logic clk, reset, enable,
                        output logic [5:0] addr0, addr1, addr2, addr3,
                        output logic done);

    logic [1:0] count;
    always_ff @(posedge clk or posedge reset) begin
        if (reset == 1'b1) begin
            addr0 <= 6'b000000;
            addr1 <= 6'b000001;
            addr2 <= 6'b001000;
            addr3 <= 6'b001001;
            count <= 2'b00;
        end

        else if (enable == 1'b1 && done == 1'b0) begin
            if(count == 2'b11) begin
                count <= 2'b00;
                addr0 <= addr0 + 6'b001010;
                addr1 <= addr1 + 6'b001010;
                addr2 <= addr2 + 6'b001010;
                addr3 <= addr3 + 6'b001010;
            end
            else begin
                addr0 <= addr0 + 6'b000010;
                addr1 <= addr1 + 6'b000010;
                addr2 <= addr2 + 6'b000010;
                addr3 <= addr3 + 6'b000010;
                count <= count + 2'b01;
            end
        end
    end
    
    always_comb begin
        //stop when addr3 == 8^2 - 1, i.e. we have processed the entire image
        if(addr3 == 6'b111111) begin
            done = 1'b1;
        end
    end

endmodule

// counter/addresser for pooling 2 layer output memory write (done)
module P2_mem_write (input logic clk, reset, enable,
                        output logic [3:0] addr0,
                        output logic done);

    always_ff @(posedge clk or posedge reset) begin
        if (reset == 1'b1) begin
            addr0 <= 4'b0000;
        end
        else if (enable == 1'b1 && done == 1'b0) begin
            addr0 <= addr0 + 4'b0001;
        end
    end
    
    always_comb begin
        //stop when addr1 == 4^2 - 1, i.e. we have processed the entire image
        if(addr0 == 4'b1111) begin
            done = 1'b1;
        end
    end

endmodule

//cycle through 4x4 input images 12 times
// counter/addresser for pooling 2 layer output memory read
module P2_mem_read (input logic clk, reset, enable,
                        output logic [3:0] addr0,
                        output logic done);
    logic [3:0] count;

    always_ff @(posedge clk or posedge reset) begin
        if (reset == 1'b1) begin
            count <= 4'b0000;
            addr0 <= 4'b0000;
        end
        else if (enable == 1'b1 && done == 1'b0) begin
            if(addr0 == 4'b1111) begin
                count <= count + 4'b0001;
                addr0 <= 4'b0000;
            end
            else begin
                addr0 <= addr0 + 4'b0001;
            end
        end
    end

    always_comb begin
        if(count == 4'b1011 && addr0 == 4'b1111) begin
            done = 1'b1;
        end
    end

endmodule

// counter/addresser for Fully connected layer weight memory read (done)
module fc_mem_read (input logic clk, reset, enable, 
                        output logic [8:0] addr0, addr1, 
                        output logic done);

    always_ff @(posedge clk or posedge reset) begin
        if (reset == 1'b1) begin
            addr0 <= 9'b000000000;
            addr1 <= 9'b011000000;
        end
        else if (enable == 1'b1 && done == 1'b0) begin
            addr0 <= addr0 + 9'b000000001;
            addr1 <= addr1 + 9'b000000001;
        end
    end

    always_comb begin
        if(addr1 == 9'b101111111)
            done = 1'b1;
    end

endmodule

hardware/mem_counter_test/P1_mem_write.vcd
$version Generated by VerilatedVcd $end
$date Thu May  5 10:34:36 2022
 $end
$timescale   1ns $end

 $scope module TOP $end
  $var wire  8 & addr0 [7:0] $end
  $var wire  8 ' addr1 [7:0] $end
  $var wire  1 # clk $end
  $var wire  1 ( done $end
  $var wire  1 % enable $end
  $var wire  1 $ reset $end
  $scope module P1_mem_write $end
   $var wire  8 & addr0 [7:0] $end
   $var wire  8 ' addr1 [7:0] $end
   $var wire  1 # clk $end
   $var wire  1 ( done $end
   $var wire  1 % enable $end
   $var wire  1 $ reset $end
  $upscope $end
 $upscope $end
$enddefinitions $end


#0
0#
0$
0%
b00000000 &
b00000000 '
0(
#10
1#
#20
0#
1$
b01001000 '
#30
1#
#40
0#
#50
1#
#60
0#
0$
#70
1#
#80
0#
1%
#90
1#
b00000001 &
b01001001 '
#90
#100
0#
#110
1#
b00000010 &
b01001010 '
#120
0#
#130
1#
b00000011 &
b01001011 '
#140
0#
#150
1#
b00000100 &
b01001100 '
#160
0#
#170
1#
b00000101 &
b01001101 '
#180
0#
#190
1#
b00000110 &
b01001110 '
#200
0#
#210
1#
b00000111 &
b01001111 '
#220
0#
#230
1#
b00001000 &
b01010000 '
#240
0#
#250
1#
b00001001 &
b01010001 '
#260
0#
#270
1#
b00001010 &
b01010010 '
#280
0#
#290
1#
b00001011 &
b01010011 '
#300
0#
#310
1#
b00001100 &
b01010100 '
#320
0#
#330
1#
b00001101 &
b01010101 '
#340
0#
#350
1#
b00001110 &
b01010110 '
#360
0#
#370
1#
b00001111 &
b01010111 '
#380
0#
#390
1#
b00010000 &
b01011000 '
#400
0#
#410
1#
b00010001 &
b01011001 '
#420
0#
#430
1#
b00010010 &
b01011010 '
#440
0#
#450
1#
b00010011 &
b01011011 '
#460
0#
#470
1#
b00010100 &
b01011100 '
#480
0#
#490
1#
b00010101 &
b01011101 '
#500
0#
#510
1#
b00010110 &
b01011110 '
#520
0#
#530
1#
b00010111 &
b01011111 '
#540
0#
#550
1#
b00011000 &
b01100000 '
#560
0#
#570
1#
b00011001 &
b01100001 '
#580
0#
#590
1#
b00011010 &
b01100010 '
#600
0#
#610
1#
b00011011 &
b01100011 '
#620
0#
#630
1#
b00011100 &
b01100100 '
#640
0#
#650
1#
b00011101 &
b01100101 '
#660
0#
#670
1#
b00011110 &
b01100110 '
#680
0#
#690
1#
b00011111 &
b01100111 '
#700
0#
#710
1#
b00100000 &
b01101000 '
#720
0#
#730
1#
b00100001 &
b01101001 '
#740
0#
#750
1#
b00100010 &
b01101010 '
#760
0#
#770
1#
b00100011 &
b01101011 '
#780
0#
#790
1#
b00100100 &
b01101100 '
#800
0#
#810
1#
b00100101 &
b01101101 '
#820
0#
#830
1#
b00100110 &
b01101110 '
#840
0#
#850
1#
b00100111 &
b01101111 '
#860
0#
#870
1#
b00101000 &
b01110000 '
#880
0#
#890
1#
b00101001 &
b01110001 '
#900
0#
#910
1#
b00101010 &
b01110010 '
#920
0#
#930
1#
b00101011 &
b01110011 '
#940
0#
#950
1#
b00101100 &
b01110100 '
#960
0#
#970
1#
b00101101 &
b01110101 '
#980
0#
#990
1#
b00101110 &
b01110110 '
#1000
0#
#1010
1#
b00101111 &
b01110111 '
#1020
0#
#1030
1#
b00110000 &
b01111000 '
#1040
0#
#1050
1#
b00110001 &
b01111001 '
#1060
0#
#1070
1#
b00110010 &
b01111010 '
#1080
0#
#1090
1#
b00110011 &
b01111011 '
#1100
0#
#1110
1#
b00110100 &
b01111100 '
#1120
0#
#1130
1#
b00110101 &
b01111101 '
#1140
0#
#1150
1#
b00110110 &
b01111110 '
#1160
0#
#1170
1#
b00110111 &
b01111111 '
#1180
0#
#1190
1#
b00111000 &
b10000000 '
#1200
0#
#1210
1#
b00111001 &
b10000001 '
#1220
0#
#1230
1#
b00111010 &
b10000010 '
#1240
0#
#1250
1#
b00111011 &
b10000011 '
#1260
0#
#1270
1#
b00111100 &
b10000100 '
#1280
0#
#1290
1#
b00111101 &
b10000101 '
#1300
0#
#1310
1#
b00111110 &
b10000110 '
#1320
0#
#1330
1#
b00111111 &
b10000111 '
#1340
0#
#1350
1#
b01000000 &
b10001000 '
#1360
0#
#1370
1#
b01000001 &
b10001001 '
#1380
0#
#1390
1#
b01000010 &
b10001010 '
#1400
0#
#1410
1#
b01000011 &
b10001011 '
#1420
0#
#1430
1#
b01000100 &
b10001100 '
#1440
0#
#1450
1#
b01000101 &
b10001101 '
#1460
0#
#1470
1#
b01000110 &
b10001110 '
#1480
0#
#1490
1#
b01000111 &
b10001111 '
1(
