hardware/mem_counter_test/P2_mem_read.sv
//cycle through 4x4 input images 12 times
// counter/addresser for pooling 2 layer output memory read
module P2_mem_read (input logic clk, reset, enable,
                        output logic [3:0] addr0,
                        output logic done);
    logic [3:0] count;

    always_ff @(posedge clk or posedge reset) begin
        if (reset == 1'b1) begin
            count <= 4'b0000;
            addr0 <= 4'b0000;
        end
        else if (enable == 1'b1 && done == 1'b0) begin
            if(addr0 == 4'b1111) begin
                count <= count + 4'b0001;
                addr0 <= 4'b0000;
            end
            else begin
                addr0 <= addr0 + 4'b0001;
            end
        end
    end

    always_comb begin
        if(count == 4'b1011 && addr0 == 4'b1111) begin
            done = 1'b1;
        end
    end

endmodule

hardware/mem_counter_test/P2_mem_read.vcd
$version Generated by VerilatedVcd $end
$date Thu May  5 10:34:48 2022
 $end
$timescale   1ns $end

 $scope module TOP $end
  $var wire  4 ' addr0 [3:0] $end
  $var wire  1 $ clk $end
  $var wire  1 ( done $end
  $var wire  1 & enable $end
  $var wire  1 % reset $end
  $scope module P2_mem_read $end
   $var wire  4 ' addr0 [3:0] $end
   $var wire  1 $ clk $end
   $var wire  4 # count [3:0] $end
   $var wire  1 ( done $end
   $var wire  1 & enable $end
   $var wire  1 % reset $end
  $upscope $end
 $upscope $end
$enddefinitions $end


#0
b0000 #
0$
0%
0&
b0000 '
0(
#10
1$
#20
0$
1%
#30
1$
#40
0$
#50
1$
#60
0$
0%
#70
1$
#80
0$
1&
#90
1$
b0001 '
#90
#100
0$
#110
1$
b0010 '
#120
0$
#130
1$
b0011 '
#140
0$
#150
1$
b0100 '
#160
0$
#170
1$
b0101 '
#180
0$
#190
1$
b0110 '
#200
0$
#210
1$
b0111 '
#220
0$
#230
1$
b1000 '
#240
0$
#250
1$
b1001 '
#260
0$
#270
1$
b1010 '
#280
0$
#290
1$
b1011 '
#300
0$
#310
1$
b1100 '
#320
0$
#330
1$
b1101 '
#340
0$
#350
1$
b1110 '
#360
0$
#370
1$
b1111 '
#380
0$
#390
b0001 #
1$
b0000 '
#400
0$
#410
1$
b0001 '
#420
0$
#430
1$
b0010 '
#440
0$
#450
1$
b0011 '
#460
0$
#470
1$
b0100 '
#480
0$
#490
1$
b0101 '
#500
0$
#510
1$
b0110 '
#520
0$
#530
1$
b0111 '
#540
0$
#550
1$
b1000 '
#560
0$
#570
1$
b1001 '
#580
0$
#590
1$
b1010 '
#600
0$
#610
1$
b1011 '
#620
0$
#630
1$
b1100 '
#640
0$
#650
1$
b1101 '
#660
0$
#670
1$
b1110 '
#680
0$
#690
1$
b1111 '
#700
0$
#710
b0010 #
1$
b0000 '
#720
0$
#730
1$
b0001 '
#740
0$
#750
1$
b0010 '
#760
0$
#770
1$
b0011 '
#780
0$
#790
1$
b0100 '
#800
0$
#810
1$
b0101 '
#820
0$
#830
1$
b0110 '
#840
0$
#850
1$
b0111 '
#860
0$
#870
1$
b1000 '
#880
0$
#890
1$
b1001 '
#900
0$
#910
1$
b1010 '
#920
0$
#930
1$
b1011 '
#940
0$
#950
1$
b1100 '
#960
0$
#970
1$
b1101 '
#980
0$
#990
1$
b1110 '
#1000
0$
#1010
1$
b1111 '
#1020
0$
#1030
b0011 #
1$
b0000 '
#1040
0$
#1050
1$
b0001 '
#1060
0$
#1070
1$
b0010 '
#1080
0$
#1090
1$
b0011 '
#1100
0$
#1110
1$
b0100 '
#1120
0$
#1130
1$
b0101 '
#1140
0$
#1150
1$
b0110 '
#1160
0$
#1170
1$
b0111 '
#1180
0$
#1190
1$
b1000 '
#1200
0$
#1210
1$
b1001 '
#1220
0$
#1230
1$
b1010 '
#1240
0$
#1250
1$
b1011 '
#1260
0$
#1270
1$
b1100 '
#1280
0$
#1290
1$
b1101 '
#1300
0$
#1310
1$
b1110 '
#1320
0$
#1330
1$
b1111 '
#1340
0$
#1350
b0100 #
1$
b0000 '
#1360
0$
#1370
1$
b0001 '
#1380
0$
#1390
1$
b0010 '
#1400
0$
#1410
1$
b0011 '
#1420
0$
#1430
1$
b0100 '
#1440
0$
#1450
1$
b0101 '
#1460
0$
#1470
1$
b0110 '
#1480
0$
#1490
1$
b0111 '
#1500
0$
#1510
1$
b1000 '
#1520
0$
#1530
1$
b1001 '
#1540
0$
#1550
1$
b1010 '
#1560
0$
#1570
1$
b1011 '
#1580
0$
#1590
1$
b1100 '
#1600
0$
#1610
1$
b1101 '
#1620
0$
#1630
1$
b1110 '
#1640
0$
#1650
1$
b1111 '
#1660
0$
#1670
b0101 #
1$
b0000 '
#1680
0$
#1690
1$
b0001 '
#1700
0$
#1710
1$
b0010 '
#1720
0$
#1730
1$
b0011 '
#1740
0$
#1750
1$
b0100 '
#1760
0$
#1770
1$
b0101 '
#1780
0$
#1790
1$
b0110 '
#1800
0$
#1810
1$
b0111 '
#1820
0$
#1830
1$
b1000 '
#1840
0$
#1850
1$
b1001 '
#1860
0$
#1870
1$
b1010 '
#1880
0$
#1890
1$
b1011 '
#1900
0$
#1910
1$
b1100 '
#1920
0$
#1930
1$
b1101 '
#1940
0$
#1950
1$
b1110 '
#1960
0$
#1970
1$
b1111 '
#1980
0$
#1990
b0110 #
1$
b0000 '
#2000
0$
#2010
1$
b0001 '
#2020
0$
#2030
1$
b0010 '
#2040
0$
#2050
1$
b0011 '
#2060
0$
#2070
1$
b0100 '
#2080
0$
#2090
1$
b0101 '
#2100
0$
#2110
1$
b0110 '
#2120
0$
#2130
1$
b0111 '
#2140
0$
#2150
1$
b1000 '
#2160
0$
#2170
1$
b1001 '
#2180
0$
#2190
1$
b1010 '
#2200
0$
#2210
1$
b1011 '
#2220
0$
#2230
1$
b1100 '
#2240
0$
#2250
1$
b1101 '
#2260
0$
#2270
1$
b1110 '
#2280
0$
#2290
1$
b1111 '
#2300
0$
#2310
b0111 #
1$
b0000 '
#2320
0$
#2330
1$
b0001 '
#2340
0$
#2350
1$
b0010 '
#2360
0$
#2370
1$
b0011 '
#2380
0$
#2390
1$
b0100 '
#2400
0$
#2410
1$
b0101 '
#2420
0$
#2430
1$
b0110 '
#2440
0$
#2450
1$
b0111 '
#2460
0$
#2470
1$
b1000 '
#2480
0$
#2490
1$
b1001 '
#2500
0$
#2510
1$
b1010 '
#2520
0$
#2530
1$
b1011 '
#2540
0$
#2550
1$
b1100 '
#2560
0$
#2570
1$
b1101 '
#2580
0$
#2590
1$
b1110 '
#2600
0$
#2610
1$
b1111 '
#2620
0$
#2630
b1000 #
1$
b0000 '
#2640
0$
#2650
1$
b0001 '
#2660
0$
#2670
1$
b0010 '
#2680
0$
#2690
1$
b0011 '
#2700
0$
#2710
1$
b0100 '
#2720
0$
#2730
1$
b0101 '
#2740
0$
#2750
1$
b0110 '
#2760
0$
#2770
1$
b0111 '
#2780
0$
#2790
1$
b1000 '
#2800
0$
#2810
1$
b1001 '
#2820
0$
#2830
1$
b1010 '
#2840
0$
#2850
1$
b1011 '
#2860
0$
#2870
1$
b1100 '
#2880
0$
#2890
1$
b1101 '
#2900
0$
#2910
1$
b1110 '
#2920
0$
#2930
1$
b1111 '
#2940
0$
#2950
b1001 #
1$
b0000 '
#2960
0$
#2970
1$
b0001 '
#2980
0$
#2990
1$
b0010 '
#3000
0$
#3010
1$
b0011 '
#3020
0$
#3030
1$
b0100 '
#3040
0$
#3050
1$
b0101 '
#3060
0$
#3070
1$
b0110 '
#3080
0$
#3090
1$
b0111 '
#3100
0$
#3110
1$
b1000 '
#3120
0$
#3130
1$
b1001 '
#3140
0$
#3150
1$
b1010 '
#3160
0$
#3170
1$
b1011 '
#3180
0$
#3190
1$
b1100 '
#3200
0$
#3210
1$
b1101 '
#3220
0$
#3230
1$
b1110 '
#3240
0$
#3250
1$
b1111 '
#3260
0$
#3270
b1010 #
1$
b0000 '
#3280
0$
#3290
1$
b0001 '
#3300
0$
#3310
1$
b0010 '
#3320
0$
#3330
1$
b0011 '
#3340
0$
#3350
1$
b0100 '
#3360
0$
#3370
1$
b0101 '
#3380
0$
#3390
1$
b0110 '
#3400
0$
#3410
1$
b0111 '
#3420
0$
#3430
1$
b1000 '
#3440
0$
#3450
1$
b1001 '
#3460
0$
#3470
1$
b1010 '
#3480
0$
#3490
1$
b1011 '
#3500
0$
#3510
1$
b1100 '
#3520
0$
#3530
1$
b1101 '
#3540
0$
#3550
1$
b1110 '
#3560
0$
#3570
1$
b1111 '
#3580
0$
#3590
b1011 #
1$
b0000 '
#3600
0$
#3610
1$
b0001 '
#3620
0$
#3630
1$
b0010 '
#3640
0$
#3650
1$
b0011 '
#3660
0$
#3670
1$
b0100 '
#3680
0$
#3690
1$
b0101 '
#3700
0$
#3710
1$
b0110 '
#3720
0$
#3730
1$
b0111 '
#3740
0$
#3750
1$
b1000 '
#3760
0$
#3770
1$
b1001 '
#3780
0$
#3790
1$
b1010 '
#3800
0$
#3810
1$
b1011 '
#3820
0$
#3830
1$
b1100 '
#3840
0$
#3850
1$
b1101 '
#3860
0$
#3870
1$
b1110 '
#3880
0$
#3890
1$
b1111 '
1(
